{
  "info": {
    "id": 41006767,
    "dataType": "판결문",
    "caseNm": "특정범죄가중처벌등에관한법률위반(관세)·관세법위반",
    "caseTitle": "대법원 1996. 9. 24. 선고 94도2332 판결",
    "courtType": "판례(대법원)",
    "courtNm": "대법원",
    "judmnAdjuDe": "1996-09-24",
    "caseNoID": "94도2332",
    "caseNo": "94도2332"
  },
  "jdgmn": "구 관세법 제181조 제2호 소정의 ‘사위 기타 부정한 방법’으로 수입승인·면허를 받은 경우에 해당하지 않는다고 본 사례",
  "jdgmnInfo": [
    {
      "question": "구 관세법 제181조 제2호 소정의 ‘사위 기타 부정한 방법’으로 수입승인·면허를 받은 경우에 해당하지 않는가?",
      "answer": "긍정"
    }
  ],
  "Summary": [
    {
      "summ_contxt": "관세법(1993. 12. 31. 개정되기 전 법률 제4027호, 이하 구 관세법이라 한다) 제181조 제2호는 부정한 방법으로 위 법 제137조의 면허를 받는 모든 유형의 행위를 처벌대상으로 하고 있는 것이 아니라, 법령이 정하는 허가, 승인, 추천 기타 조건을 사위 기타 부정한 방법으로 구비하여 제137조의 면허를 받는 행위만을 처벌대상으로 규정하고 있다. 원심이 위 설치승인서 사본의 제출은 구 관세법 제181조 제2호 소정의 법령이 정하는 승인 기타 조건에 해당된다고 할 수 없고, 위 협동조합으로서는 수입업자가 무역관계 법령 및 통합공고, 수입신고세부요령 등에서 정한대로 서류를 갖추어 수입신고를 하면 수입신고 사실을 확인하여 줄 의무가 있으며, 그 위에 이 사건에서 문제된 보건사회부의 행정지침인 ‘고가의료장비 수입신고에 따른 지침’과 같이 수입신고요령으로 공고되지 아니한 사유를 들어 그 신고의 수리를 거부할 수는 없으므로, 김충호가 위 지침에 위배하여 다른 피고인들에게 수입신고 확인을 하여 준 행위가 검사가 주장하는 것과 같은 사위 기타 부정한 방법에 해당하지 않는다고 하여 피고인들에 대하여 무죄를 선고한 제1심 판결을 그대로 유지한 원심의 조치는 정당하고, 거기에 소론과 같은 구 관세법 제181조 제2호에 관한 법리를 오해한 위법이 있다고 할 수 없다.",
      "summ_pass": "고가특수의료장비 설치승인을 받은 경우에만 그 수입신고를 받아 주도록 규정한 보건사회부훈령 제551호에 위배하여 수입신고 확인을 하여 준 행위가 구 관세법(1993. 12. 31. 법률 제4674호로 개정되기 전의 것) 제181조 제2호 소정의 ‘법령이 정하는 허가·승인·추천 기타 조건을 사위 기타 부정한 방법으로 구비한’ 경우에 해당하지 않는다고 한 원심판결을 수긍한다."
    }
  ],
  "keyword_tagg": [
    {
      "id": 1,
      "keyword": "사위 기타 부정한 방법"
    },
    {
      "id": 2,
      "keyword": "법리 오해"
    }
  ],
  "Reference_info": {
    "reference_rules": "구 관세법(1993. 12. 31. 법률 제4674호로 개정되기 전의 것) 제181조 제2호, 제137조",
    "reference_court_case": ""
  },
  "Class_info": {
    "class_name": "형사B(일반형)",
    "instance_name": "특정범죄가중처벌등에관한법률위반(관세)"
  }
}