{
  "info": {
    "id": 42042411,
    "dataType": "판결문",
    "caseNm": "배당이의",
    "caseTitle": "대법원 2000. 12. 26. 선고 2000다56204 판결",
    "courtType": "판례(대법원)",
    "courtNm": "대법원",
    "judmnAdjuDe": "2000-12-26",
    "caseNoID": "2000다56204",
    "caseNo": "2000다56204"
  },
  "jdgmn": "근저당권에 관하여 채무인수를 원인으로 채무자를 교체하는 변경등기(부기등기)가 마쳐진 경우, 그 근저당권은 채무인수인이 다른 원인으로 부담하게 된 새로운 채무까지 담보하는지 여부(소극)",
  "jdgmnInfo": [
    {
      "question": "근저당권에 관하여 채무인수를 원인으로 채무자를 교체하는 변경등기가 마쳐진 경우, 그 근저당권은 채무인수인이 다른 원인으로 부담하게 된 새로운 채무까지 담보하는 것으로 볼 수 있는지?",
      "answer": "부정"
    }
  ],
  "Summary": [
    {
      "summ_contxt": "채무가 인수되는 경우에 구 채무자의 채무에 관하여 제3자가 제공한 담보는 채무인수로 인하여 소멸하되 다만 그 제3자(물상보증인)가 채무인수에 동의한 경우에 한하여 소멸하지 아니하고 신 채무자를 위하여 존속하게 되는바, 이 경우 물상보증인이 채무인수에 관하여 하는 동의는 채무인수인을 위하여 새로운 담보를 설정하겠다는 의사표시가 아니라 기존의 담보를 채무인수인을 위하여 계속 유지하겠다는 의사표시에 불과하여 그 동의에 의하여 유지되는 담보는 기존의 담보와 동일한 내용을 갖는 것이므로, 근저당권에 관하여 채무인수를 원인으로 채무자를 교체하는 변경등기(부기등기)가 마쳐진 경우 특별한 사정이 없는 한 그 근저당권은 당초 구 채무자가 부담하고 있다가 신 채무자가 인수하게 된 채무만을 담보하는 것이지, 그 후 신 채무자(채무인수인)가 다른 원인으로 부담하게 된 새로운 채무까지 담보하는 것으로 볼 수는 없다.",
      "summ_pass": "채무인수의 경우, 구 채무자의 채무에 관하여 물상보증인이 제공한 담보는 채무인수로 소멸하나 물상보증인이 동의한 경우에 한하여 신 채무를 위한 담보는 계속 존속하게 되는데, 이 경우 물상보증인의 담보설정의 의미는 기존의 담보와 동일한 내용으로 계속 유지하겠다는 의사표시에 불과한 것으로써, 근저당권에 관하여 채무인수를 원인으로 채무자를 교체하는 변경등기가 마쳐진 경우, 그 근저당권은 채무인수인이 다른 원인으로 부담하게 된 새로운 채무까지 담보하는 것으로 볼 수 없다."
    }
  ],
  "keyword_tagg": [
    {
      "id": 1,
      "keyword": "변경등기"
    },
    {
      "id": 2,
      "keyword": "채무인수"
    },
    {
      "id": 3,
      "keyword": "물상보증인"
    }
  ],
  "Reference_info": {
    "reference_rules": "민법 제357조, 제459조",
    "reference_court_case": "대법원 1996. 10. 11. 선고 96다27476 판결(공1996하, 3325), 대법원 1999. 9. 3. 선고 98다40657 판결(공1999하, 2026)"
  },
  "Class_info": {
    "class_name": "민사",
    "instance_name": "배당이의"
  }
}