{
  "info": {
    "id": 44059577,
    "dataType": "판결문",
    "caseNm": "정보공개거부처분취소청구",
    "caseTitle": "국민권익위원회 2001-03910, 2001. 6. 25.",
    "courtType": "심결례",
    "courtNm": "국민권익위원회",
    "judmnAdjuDe": "2001-06-25",
    "caseNoID": "2001-03910",
    "caseNo": "2001-03910"
  },
  "jdgmn": "",
  "jdgmnInfo": [
    {
      "question": "고등학교 집단괴롭힘 사건과 관련된 일체의 자료에 대한 정보공개청구를 하자 피청구인이 위 정보는 진행중인 재판에 관련된 것으로서 비공개대상정보라는 이유로 정보공개거부처분이 합당한가?",
      "answer": "긍정"
    }
  ],
  "Summary": [
    {
      "summ_contxt": "공공기관의정보공개에관한법률에 의하면 다른 법률 또는 법률에 의한 명령에 의하여 비밀로 유지되거나 비공개사항으로 규정된 정보 및 진행중인 재판에 관련된 정보와 범죄의 예방, 수사, 공소의 제기 및 유지, 형의 집행, 교정, 보안처분에 관한 사항으로서 공개될 경우 그 직무수행을 현저히 곤란하게 하거나 형사피고인의 공정한 재판을 받을 권리를 침해한다고 인정할 만한 상당한 이유가 있는 정보에 대하여는 이를 공개하지 아니할 수 있는바, 위 인정사실에 의하면, 이 사건과 관련하여 가해학생과 교사 등을 상대로 민·형사재판이 진행중에 있어 청구인이 공개를 청구한 정보를 공개할 경우 상대방의 소송수행에 영향을 미칠 수도 있고, 또한 이 사건의 직접 당사자인 가해학생과 교사들이 정보공개에 동의하지 않고 있는 점 등을 고려할 때, 청구인이 신청한 자료의 공개를 거부한 피청구인의 이 건 처분이 위법·부당하다고 할 수 없을 것이다.",
      "summ_pass": "정보에 대하여는 이를 공개하지 아니할 수 있는바, 위 인정사실에 의하면, 이 사건과 관련하여 가해학생과 교사 등을 상대로 민·형사재판이 진행중에 있어 청구인이 공개를 청구한 정보를 공개할 경우 상대방의 소송수행에 영향을 미칠 수도 있고, 또한 이 사건의 직접 당사자인 가해학생과 교사들이 정보공개에 동의하지 않고 있는 점 등을 고려할 때, 청구인이 신청한 자료의 공개를 거부한 피청구인의 이 건 처분이 위법·부당하다고 할 수 없을 것이다."
    }
  ],
  "keyword_tagg": [
    {
      "id": 1,
      "keyword": "공공기관의정보공개에관한법률"
    },
    {
      "id": 2,
      "keyword": "재판을 받을 권리"
    }
  ],
  "Reference_info": {
    "reference_rules": "공공기관의정보공개에관한법률 제7조제1항, 제9조제3항",
    "reference_court_case": ""
  },
  "Class_info": {
    "class_name": "개인정보/ICT",
    "instance_name": "행정처분취소"
  }
}