{
  "info": {
    "id": 57626519,
    "dataType": "판결문",
    "caseNm": "정보공개이행청구",
    "caseTitle": "국민권익위원회 2001-03747, 2001. 5. 28.",
    "courtType": "심결례",
    "courtNm": "국민권익위원회",
    "judmnAdjuDe": "2001-05-28",
    "caseNoID": "2001-03747",
    "caseNo": "2001-03747"
  },
  "jdgmn": "",
  "jdgmnInfo": [
    {
      "question": "청구인이 공개정구하는 정보가 피청구인이 직무상 작성한 자료가 아닐뿐 아니라 달리 직무상 이를 취득하여 보유하고 있다고 볼 만한 근거도 없다면 이 건 정보는 공개하지 않아도 되는가?",
      "answer": "긍정"
    }
  ],
  "Summary": [
    {
      "summ_contxt": "살피건대, 공공기관의정보공개에관한법률 제2조의 규정에 의하면, 정보라 함은 공공기관이 직무상 작성 또는 취득하여 관리하고 있는 문서·도면·사진·필름·테이프·슬라이드 및 컴퓨터에 의하여 처리되는 매체등에 기록된 사항을 말한다고 규정되어 있고, 국민건강보험법 제55조 및 제56조의 규정에 의하면, 요양급여비용을 심사하고 요양급여의 적정성을 평가하기 위하여 건강보험심사평가원을 설립하여 1. 요양급여비용의 심사, 2. 요양급여의 적정성에 대한 평가, 3. 심사 및 평가 기준의 개발, 4. 제1호 내지 제3호의 업무와 관련된 조사연구 및 국제협력, 5. 다른 법률의 규정에 의하여 지급되는 급여비용의 심사 또는 의료의 적정성 평가에 관하여 위탁받은 업무, 6. 건강보험과 관련하여 보건복지부장관이 필요하다고 인정한 업무, 7. 기타 보험급여비용의 심사와 보험급여의 적정성 평가와 관련하여 대통령령이 정하는 업무를 관장하도록 하고 있는 바, 관계법령의 규정과 제출된 자료에 의하면, 청구인이 공개청구한 정보내용중 신문기사에 관련된 자료는 청구인이 해당 언론기관에 자료를 제공한 것이 아니라 언론기관의 취재활동에 의한 것이고, 진료비 평가 및 보험재정누수와 관련된 자료, 약국의 처방전수용실태 관련자료, 의료기관의 특정제약회사 의약품사용실태 관련자료, 오리지날제품(○○의약품) 사용현황 자료들은 요양급여비용의 심사, 요양급여의 적정성에 대한 평가, 심사 및 평가기준에 관한 것으로 이는 요양급여비용을 심사하고 요양급여의 적정성을 평가하기 위하여 설립된 건강보험심사평가원에서 직무상 작성 또는 취득하여 관리하고 있는 자료라 할 것이어서, 피청구인이 직무상 작성한 자료가 아닐뿐 아니라 달리 직무상 이를 취득하여 보유하고 있다고 볼 만한 근거도 없다 할 것이다. 따라서, 피청구인이 청구인의 정보공개청구에 따라 이를 공개하지 아니한 것이 위법·부당하다고 할 수 없을 것이다.",
      "summ_pass": "공공기관의정보공개에관한법률 제2조의 규정에 의하면, 정보라 함은 공공기관이 직무상 작성 또는 취득하여 관리하고 있는 문서·도면·사진·필름·테이프·슬라이드 및 컴퓨터에 의하여 처리되는 매체등에 기록된 사항을 말한다고 규정되어 있고, 관계법령의 규정과 제출된 자료에 의하면, 청구인이 공개청구한 정보내용중 신문기사에 관련된 자료는 청구인이 해당 언론기관에 자료를 제공한 것이 아니라 언론기관의 취재활동에 의한 것이고, 진료비 평가 및 보험재정누수와 관련된 자료, 약국의 처방전수용실태 관련자료, 의료기관의 특정제약회사 의약품사용실태 관련자료, 오리지날제품(○○의약품) 사용현황 자료들은 요양급여비용의 심사, 요양급여의 적정성에 대한 평가, 심사 및 평가기준에 관한 것으로 이는 요양급여비용을 심사하고 요양급여의 적정성을 평가하기 위하여 설립된 건강보험심사평가원에서 직무상 작성 또는 취득하여 관리하고 있는 자료라 할 것이어서, 피청구인이 직무상 작성한 자료가 아닐뿐 아니라 달리 직무상 이를 취득하여 보유하고 있다고 볼 만한 근거도 없다."
    }
  ],
  "keyword_tagg": [
    {
      "id": 1,
      "keyword": "공공기관의정보공개에관한법률"
    },
    {
      "id": 2,
      "keyword": "공개청구"
    },
    {
      "id": 3,
      "keyword": "직무상 작성한 자료"
    }
  ],
  "Reference_info": {
    "reference_rules": "",
    "reference_court_case": ""
  },
  "Class_info": {
    "class_name": "개인정보/ICT",
    "instance_name": "정보공개이행청구"
  }
}