{
  "info": {
    "id": 42057859,
    "dataType": "판결문",
    "caseNm": "권리범위확인(상)",
    "caseTitle": "대법원 2006. 2. 9. 선고 2003후2690 판결",
    "courtType": "판례(대법원)",
    "courtNm": "대법원",
    "judmnAdjuDe": "2006-02-09",
    "caseNoID": "2003후2690",
    "caseNo": "2003후2690"
  },
  "jdgmn": "상표권이 소멸한 경우 권리범위확인의 이익 유무(소극)",
  "jdgmnInfo": [
    {
      "question": "상표권이 소멸한 경우 권리범위확인의 이익이 있는가?",
      "answer": "부정"
    }
  ],
  "Summary": [
    {
      "summ_contxt": "상표권의 권리범위확인심판의 청구는 현존하는 상표권의 범위를 확정하려는 데에 그 목적이 있으므로, 일단 적법하게 발생한 상표권이라 할지라도 그 상표권이 소멸된 이후에는 그에 대한 권리범위확인을 구할 이익은 없어진다(대법원 2002. 2. 22. 선고 2001후2474 판결, 2002. 4. 23. 선고 2000후2439 판결 등 참조).",
      "summ_pass": "상표권이 소멸한 경우 권리범위확인의 이익이 없다."
    }
  ],
  "keyword_tagg": [
    {
      "id": 1,
      "keyword": "권리범위확인"
    }
  ],
  "Reference_info": {
    "reference_rules": "상표법 제75조",
    "reference_court_case": "대법원 1996. 9. 10. 선고 94후2223 판결(공1996하, 3017), 대법원 2002. 2. 22. 선고 2001후2474 판결"
  },
  "Class_info": {
    "class_name": "특허/저작권",
    "instance_name": "권리범위확인"
  }
}