{
  "info": {
    "id": 41013266,
    "dataType": "판결문",
    "caseNm": "양도소득세부과처분취소",
    "caseTitle": "대법원 2004. 11. 25. 선고 2003두12929 판결",
    "courtType": "판례(대법원)",
    "courtNm": "대법원",
    "judmnAdjuDe": "2004-11-25",
    "caseNoID": "2003두12929",
    "caseNo": "2003두12929"
  },
  "jdgmn": "[1] 법령이 전문 개정된 경우, 전문 개정 전 부칙 규정은 소멸하는지 여부(적극)\n[2] 조세법령이 납세의무자에게 불리하게 개정된 경우, 납세의무자의 기득권 내지 신뢰 보호를 위하여 납세의무자에게 유리한 종전 규정을 적용하기 위한 요건\n[3] 전문 개정된 조세특례제한법령이 시행된 1999. 1. 1. 이후에 양도된 농지의 경우, 자경농지에 대한 양도소득세의 면제에 관하여 종전의 통작거리규정이 적용되지 않는다고 한 사례",
  "jdgmnInfo": [
    {
      "question": "전문 개정된 조세특례제한법령이 시행된 1999. 1. 1. 이후에 양도된 농지의 경우, 자경농지에 대한 양도소득세의 면제에 관하여 종전의 통작거리규정이 적용되는가?",
      "answer": "부정"
    }
  ],
  "Summary": [
    {
      "summ_contxt": "1998. 12. 28. 법률 제5584호로 전문 개정된 조세특례제한법 제69조 제1항 제1호와 1998. 12. 31. 대통령령 제15976호로 전문 개정된 조세특례제한법시행령 제66조 제4항은 전문 개정 전의 구 조세감면규제법령의 면제규정을 그대로 이어받았으나, 부칙에서 통작거리규정과 관련하여서는 아무런 경과규정을 두지 아니하고, 다만 조세특례제한법 부칙 제9조 제2항에서 \"이 법 시행일 전에 종전의 규정에 의하여 감면하였거나 감면할 국세 및 지방세에 관하여는 종전의 규정에 의한다.\"는 일반적 경과규정을 두었으며, 위와 같이 전문 개정된 조세특례제한법령의 규정은 1999. 1. 1. 이후 최초로 양도하는 분부터 적용된다.",
      "summ_pass": "전문 개정된 조세특례제한법령이 시행된 1999. 1. 1. 이후에 양도된 농지의 경우, 자경농지에 대한 양도소득세의 면제에 관하여 종전의 통작거리규정이 적용되지 않는다."
    }
  ],
  "keyword_tagg": [
    {
      "id": 1,
      "keyword": "통작거리"
    },
    {
      "id": 2,
      "keyword": "경과규정"
    }
  ],
  "Reference_info": {
    "reference_rules": "[1] 구 조세감면규제법(1998. 12. 28. 법률 제5584호 조세특례제한법으로 전문 개정되기 전의 것) 제55조 제1항 제1호(현행조세특례제한법 제69조 제1항 제1호 참조) 구 조세감면규제법시행령(1995. 12. 30. 대통령령 제14869호로 개정되기 전의 것) 제54조 제2항 제3호(현행 삭제), 부칙(1995. 12. 30.) 제10조 제3항 / 구 조세특례제한법(1999. 3. 12. 대통령령 제16184호로 개정되기 전의 것) 제69조 제1항 제1호, 부칙(1998. 12. 28.) 제9조 제2항 / 구 조세특례제한법시행령(1999. 3. 12. 대통령령 제16184호로 개정되기 전의 것) 제66조 제4항 [2] 구 조세감면규제법(1998. 12. 28. 법률 제5584호 조세특례제한법으로 전문 개정되기 전의 것) 제55조 제1항 제1호(현행조세특례제한법 제69조 제1항 제1호 참조) 구 조세감면규제법시행령(1995. 12. 30. 대통령령 제14869호로 개정되기 전의 것) 제54조 제2항 제3호(현행 삭제), 부칙(1995. 12. 30.) 제10조 제3항 / 구 조세특례제한법(1999. 3. 12. 대통령령 제16184호로 개정되기 전의 것) 제69조 제1항 제1호, 부칙(1998. 12. 28.) 제9조 제2항 / 구 조세특례제한법시행령(1999. 3. 12. 대통령령 제16184호로 개정되기 전의 것) 제66조 제4항 [3] 구 조세감면규제법(1998. 12. 28. 법률 제5584호 조세특례제한법으로 전문 개정되기 전의 것) 제55조 제1항 제1호(현행조세특례제한법 제69조 제1항 제1호 참조) 구 조세감면규제법시행령(1995. 12. 30. 대통령령 제14869호로 개정되기 전의 것) 제54조 제2항 제3호(현행 삭제), 부칙(1995. 12. 30.) 제10조 제3항 / 구 조세특례제한법(1999. 3. 12. 대통령령 제16184호로 개정되기 전의 것) 제69조 제1항 제1호, 부칙(1998. 12. 28.) 제9조 제2항 / 구 조세특례제한법시행령(1999. 3. 12. 대통령령 제16184호로 개정되기 전의 것) 제66조 제4항",
    "reference_court_case": "[1] 대법원 2002. 7. 26. 선고 2001두11168 판결(공2002하, 2091), 대법원 2004. 6. 24. 선고 2002두10780 판결(공2004하, 1249) [2] 대법원 2001. 5. 29. 선고 98두13713 판결(공2001하, 1523)"
  },
  "Class_info": {
    "class_name": "금융조세",
    "instance_name": "양도소득세"
  }
}