{
  "info": {
    "id": 43000004,
    "dataType": "판결문",
    "caseNm": "시정명령등취소",
    "caseTitle": "서울고등법원 2007. 1. 17. 선고 2004누17480 판결 : 상고",
    "courtType": "판례(하급심)",
    "courtNm": "서울고등법원",
    "judmnAdjuDe": "2007-01-17",
    "caseNoID": "2004누17480",
    "caseNo": "2004누17480"
  },
  "jdgmn": "[1] 동일·유사한 상품의 가격이 외형상 상이한 경우, 구 독점규제 및 공정거래에 관한 법률 제19조 제1항 제1호에 정한 상품의 가격결정행위에 ‘외형상 일치’가 있는지 여부의 판단 기준\n[2] 아파트의 분양가가 동일하거나 거의 비슷하다는 외형상 일치를 보이고 있지 않더라도 개별특성에 따른 차이를 배제하면 분양가가 실질적으로 일치한다고 인정되는 경우, 분양가책정행위의 외형상 일치를 인정할 수 있다고 본 사례\n[3] 대규모 택지개발지구에서 건설회사들이 협의체를 구성하고 아파트를 분양하면서 거의 대부분의 아파트에 중도금 이자후불제를 시행한 행위에 대하여, 부당한 공동행위의 합의를 추정하기 위한 ‘행위의 외형상 일치’와 ‘실질적 경쟁제한성’이 인정되고 그 합의추정을 복멸시킬 수 없다고 한 사례\n[4] 구 독점규제 및 공정거래에 관한 법률 제2조 제8호, 제19조 제5항에서 말하는 ‘일정한 거래분야’의 판단 기준\n[5] 대규모 택지개발지구 사업에 의하여 아파트를 분양하는 경우, 구 독점규제 및 공정거래에 관한 법률 제2조 제8호, 제19조 제5항에서 말하는 ‘일정한 거래분야’라 함은 ‘대규모 동시 분양이 있었던 지구의 신규분양 아파트 시장’이라고 본 사례",
  "jdgmnInfo": [
    {
      "question": "아파트의 분양가가 거의 비슷하지 않더라도 개별특성에 따른 차이를 배제하면 분양가가 실질적으로 일치하는 경우 분양가책정행위의 외형상 일치를 인정할 수 있는가?",
      "answer": "긍정"
    }
  ],
  "Summary": [
    {
      "summ_contxt": "상품의 가격결정(구 독점규제 및 공정거래에 관한 법률 제19조 제1항 제1호)에 관한 합의가 문제되는 사안에서, ‘사업자들의 행위의 외형상 일치’가 있다고 함은 비단 사업자들이 동일한 상품에 대하여 동일하게 최종거래 가격을 정하는 경우뿐만 아니라, 동일·유사한 상품에 대하여 평균가격, 표준가격, 기준가격, 최고·최저가격 등 가격결정의 기준을 정하는 행위, 가격인상·인하율(폭)을 정하는 행위, 이윤율, 할인율 등 가격의 구성요소에 관하여 그 수준이나 한도를 정하는 행위 등을 통하여 실질적으로 동일한 수준의 가격을 결정하는 행위를 하고 있는 경우도 모두 포함한다. 비록 각 상품의 가격이 외형상으로는 상이하더라도 그 차이가 가격협정 외의 다른 사유 즉 회사별·상품별 특성에서 비롯된 당연한 결과여서 그러한 차이를 일으키는 요소들을 배제하면 가격의 본질적 부분에서 일치하게 되는 경우에는 전체적으로 보아 각 상품의 가격결정행위가 일치한다고 보아야 할 것이다.",
      "summ_pass": "‘사업자들의 행위의 외형상 일치’가 있다고 함은 동일한 상품에 대하여 동일하게 최종거래 가격을 정하는 경우뿐 아니라, 상품의 가격이 상이하더라도 가격의 본질적 부분에서 일치하게 되는 경우에는 전체적으로 보아 각 상품의 가격결정행위가 일치한다고 보아야 한다. 따라서 아파트의 분양가가 외형상 일치를 보이고 있지 않더라도 개별특성에 따른 차이를 배제하면 분양가가 실질적으로 일치한다고 인정되는 경우, 분양가책정행위의 외형상 일치를 인정할 수 있다."
    }
  ],
  "keyword_tagg": [
    {
      "id": 1,
      "keyword": "가격결정행위"
    }
  ],
  "Reference_info": {
    "reference_rules": "[1] 구 독점규제 및 공정거래에 관한 법률(2004. 12. 31. 법률 제7315호로 개정되기 전의 것) 제19조 제1항 제1호, 제5항 [2] 구 독점규제 및 공정거래에 관한 법률(2004. 12. 31. 법률 제7315호로 개정되기 전의 것) 제19조 제1항 제2호, 제5항 [3] 구 독점규제 및 공정거래에 관한 법률(2004. 12. 31. 법률 제7315호로 개정되기 전의 것) 제19조 제1항 제2호, 제5항 [4] 구 독점규제 및 공정거래에 관한 법률 제2조 제8호, 제19조 제5항 [5] 구 독점규제 및 공정거래에 관한 법률 제2조 제8호, 제19조 제5항",
    "reference_court_case": ""
  },
  "Class_info": {
    "class_name": "기업",
    "instance_name": "공정거래법"
  }
}