{
  "info": {
    "id": 38021687,
    "dataType": "판결문",
    "caseNm": "일반건설업영업정지처분취소청구",
    "caseTitle": "국민권익위원회 2004-00353, 2004. 2. 23.",
    "courtType": "심결례",
    "courtNm": "국민권익위원회",
    "judmnAdjuDe": "2004-02-23",
    "caseNoID": "2004-00353",
    "caseNo": "2004-00353"
  },
  "jdgmn": "",
  "jdgmnInfo": [
    {
      "question": "일반건설업 등록기준의 하나로 건설업에서 7년 이상 관리책임자로 종사한 자를 임원 중 1인으로 해야 하는가?",
      "answer": "긍정"
    }
  ],
  "Summary": [
    {
      "summ_contxt": "건설교통부장관 또는 시·도지사는 건설업자가 위 건설업의 등록기준에 미달한 사실이 있는 때에는 당해 건설업자의 건설업 등록을 말소하거나 1년 이내의 기간을 정하여 영업의 정지를 명할 수 있다고 규정하고 있고, 동법시행령 제80조 및 별표 6에 의하면, 건설업의 등록기준에 미달하게 된 때에는 6월의 영업정지를 명하면서 그 위반행위의 동기·내용 및 횟수 등을 참작하여 영업정지 기간의 2분의 1의 범위 안에서 이를 가중 또는 감경할 수 있다고 규정하고 있는바, 청구인이 1년 4월 이상의 기간 동안 경력임원을 보유하지 아니한 사실이 분명하고, 동법시행령상 2003. 12. 31.까지는 경력임원의 보유가 건설업 등록기준의 하나로서 요구되는 사실 또한 명백하므로 청구인의 제반 사정을 참작하여 한 5월의 영업정지처분이 청구인에게 지나치게 가혹하다고는 볼 수 없다 할 것이다. 따라서 관련규정에 따른 피청구인의 이 건 처분이 위법·부당하다고 할 수 없을 것이다.",
      "summ_pass": "청구인이 1년 4월 이상의 기간 동안 경력임원을 보유하지 아니하여, 등록기준 미달이 분명하다. 청구인의 제반 사정을 참작하여 한 영업정지처분이 지나치게 가혹하다고는 볼 수 없어 피청구인의 처분이 위법·부당하다고 할 수 없다."
    }
  ],
  "keyword_tagg": [
    {
      "id": 1,
      "keyword": "영업정지처분"
    },
    {
      "id": 2,
      "keyword": "제반 사정"
    }
  ],
  "Reference_info": {
    "reference_rules": "건설산업기본법 제9조, 제10조, 제83조, 제84조, 제86조 및 제91조 건설산업기본법시행령 제13조제1항, 제80조, 제86조제1항, 부칙 제3조 및 별표 6 건설산업기본법시행령(2003. 8. 21. 대통령령 제18092호로 개정·시행되기 이전의 것) 제13조제1항",
    "reference_court_case": ""
  },
  "Class_info": {
    "class_name": "행정",
    "instance_name": "행정처분취소"
  }
}