{
  "info": {
    "id": 41016374,
    "dataType": "판결문",
    "caseNm": "사기",
    "caseTitle": "대법원 2006. 3. 16. 선고 2005도9729 전원합의체 판결",
    "courtType": "판례(대법원)",
    "courtNm": "대법원",
    "judmnAdjuDe": "2006-03-16",
    "caseNoID": "2005도9729",
    "caseNo": "2005도9729"
  },
  "jdgmn": "상소장 제출에 관하여 재소자에 대한 특칙을 규정한 형사소송법 제344조 제1항이 상소이유서 제출에 관하여도 준용될 수 있는지 여부(적극)",
  "jdgmnInfo": [
    {
      "question": "상소장 제출에 관하여 재소자에 대한 특칙을 규정한 형사소송법 제344조 제1항이 상소이유서 제출에 관하여도 준용될 수 있는가?",
      "answer": "긍정"
    }
  ],
  "Summary": [
    {
      "summ_contxt": "[다수의견] 원래 형사소송법이 재소자에 대한 특칙을 두어 상소장 법원 도달주의의 예외를 인정한 취지는, 재소자로서 교도소나 구치소에 구금되어 행동의 자유가 박탈되어 있는 자가 상소심 재판을 받기 위한 상소장 제출을 위하여 할 수 있는 행위는 구금당하고 있는 교도소 등의 책임자나 그 직무대리자에게 상소장을 제출하여 그들로 하여금 직무상 해당 법원에 전달케 하는 것이 통상적인 방법이라는 점을 고려하여 재소자에게 상소 제기에 관한 편의를 제공하자는 데 있다. 그런데 피고인으로서는 적법한 상소이유서 제출에 의하여 비로소 자신이 주장하는 상소이유에 대하여 심판 받을 수 있으므로 상소이유서는 상소장과 함께 상소심 심판을 받기 위하여 반드시 제출이 요구되는 것이고, 그 기간의 장단(長短)에 차이가 있을 뿐 상소이유서 제출의 방법에 있어서는 상소장과 그 사정이 전혀 다를 바 없다.",
      "summ_pass": "상소이유서는 상소장과 함께 상소심 심판을 받기 위하여 반드시 제출이 요구되는 것이고, 그 기간의 장단(長短)에 차이가 있을 뿐 상소이유서 제출의 방법에 있어서는 상소장과 그 사정이 전혀 다를 바 없다."
    }
  ],
  "keyword_tagg": [
    {
      "id": 1,
      "keyword": "통상적인 방법"
    },
    {
      "id": 2,
      "keyword": "형사소송법"
    }
  ],
  "Reference_info": {
    "reference_rules": "형사소송법 제344조 제1항, 제355조, 제430조, 제490조 제2항",
    "reference_court_case": "대법원 1959. 7. 20. 선고 4292형상261 판결, 대법원 1963. 5. 2.자 63로5 결정(폐기), 대법원 1963. 6. 13. 선고 63도121 판결(폐기), 대법원 1964. 5. 21. 선고 64도87 전원합의체 판결(집12-1, 형28)(폐기), 대법원 1967. 5. 20.자 67모24 결정(폐기), 대법원 1969. 11. 26.자 69모84 결정(폐기), 대법원 1984. 10. 11.자 84모57 결정(공1985, 44)(폐기), 대법원 2000. 6. 20.자 2000모69 결정(공2000하, 1850)(폐기)"
  },
  "Class_info": {
    "class_name": "형사A(생활형)",
    "instance_name": "사기"
  }
}