{
  "info": {
    "id": 41000894,
    "dataType": "판결문",
    "caseNm": "독점규제및공정거래에관한법률위반",
    "caseTitle": "서울중앙지방법원 2006. 6. 16. 선고 2005라57 결정",
    "courtType": "판례(하급심)",
    "courtNm": "서울중앙지방법원",
    "judmnAdjuDe": "2006-06-16",
    "caseNoID": "2005라57",
    "caseNo": "2005라57"
  },
  "jdgmn": "",
  "jdgmnInfo": [
    {
      "question": "공정거래법 제11조의2 소정의 이사회 의결 및 공시의무부과는 부당지원행위를 억제하려는 목적도 있다는 점에서 기업간의 내부거래가 아닌 실질적인 중개행위가 있다 하더라도 공정거래법 제11조의2 소정의 공시대상이 된다고 볼 수 있는가?",
      "answer": "긍정"
    }
  ],
  "Summary": [
    {
      "summ_contxt": "① 공정거래법과 시행령은 거래금액을 기준으로 대규모내부거래를 정의하고 있을 뿐 중개수수료와 같은 수익규모를 기준으로 이를 정하고 있지 아니할 뿐만 아니라 대규모내부거래의 범주에서 중개거래를 제외하고 있지도 않고, ② 대규모내부거래에 대한 이사회의결 및 공시에 관한 규정(2002. 5. 6. 개정된 공정거래위원회고시 제2002-05호, 이하 이 사건 공시규정이라 한다) 제4조 제1항 제2호는 주식 또는 회사채 등 유가증권의 직접거래와 특수관계인이 아닌 제3자의 중개 등을 통하여 간접적으로 유가증권을 제공 또는 거래하는 행위도 대규모내부거래에 포함된다고 규정하고 있으며, ③ 항고인은 기업어음 또는 회사채 등의 매매거래를 중개함에 있어 항고인이 매도인 또는 매수인의 지위에서 당사자로서 거래하는 형식을 취하고, 매매거래의 이행도 항고인을 거쳐 이루어지는 이상 법률적으로는 항고인이 매매대금 등의 지급의무를 부담하게 되고, 따라서 항고인이 법률상 거래의 주체가 되는 것이고, ④ 계열회사가 실질적으로 기업어음 또는 회사채를 매도나 매입하는 경우는 물론 중개거래의 경우에도 계열회사를 상대방으로 하여 기업어음이나 회사채를 고가나 저가로 매도 또는 매입하게 하는 등의 방법으로 부당지원행위가 이루어질 수 있는데, 공정거래법 제11조의2 소정의 이사회 의결 및 공시의무부과는 부당지원행위를 억제하려는 목적도 있다는 점에서 중개행위의 경우에도 이사회 의결 및 공시의무를 부과할 필요성이 있으므로, 항고인의 주장과 같이 별지 1 기재 각 거래 중 실질적인 중개행위가 있다 하더라도 공정거래법 제11조의2 소정의 공시대상이 된다고 할 것이다. 따라서 항고인의 위 주장은 받아들일 수 없다.",
      "summ_pass": "공정거래법 제11조의2 소정의 이사회 의결 및 공시의무부과는 부당지원행위를 억제하려는 목적도 있다는 점에서 중개행위의 경우에도 이사회 의결 및 공시의무를 부과할 필요성이 있으므로, 항고인의 주장과 같이 별지 1 기재 각 거래 중 실질적인 중개행위가 있다 하더라도 공정거래법 제11조의2 소정의 공시대상이 된다고 할 것이다. 따라서 항고인의 위 주장은 받아들일 수 없다."
    }
  ],
  "keyword_tagg": [
    {
      "id": 1,
      "keyword": "대규모내부거래"
    },
    {
      "id": 2,
      "keyword": "공정거래위원회"
    }
  ],
  "Reference_info": {
    "reference_rules": "공정거래법 제11조의2",
    "reference_court_case": ""
  },
  "Class_info": {
    "class_name": "기업",
    "instance_name": "독점규제및공정거래에관한법률위반"
  }
}