{
  "info": {
    "id": 41003650,
    "dataType": "판결문",
    "caseNm": "자동차손해배상보장법위반",
    "caseTitle": "대법원 2007. 6. 29. 선고 2006도2960 판결",
    "courtType": "판례(대법원)",
    "courtNm": "대법원",
    "judmnAdjuDe": "2007-06-29",
    "caseNoID": "2006도2960",
    "caseNo": "2006도2960"
  },
  "jdgmn": "의료기관이 보험사업자등에게 자동차보험 진료수가를 청구함에 있어서 영상진단에 대한 판독소견서를 작성·비치하지 않은 채 영상진단 판독료를 청구한 행위가 자동차손해배상 보장법 제11조 제3항 위반에 해당하는 경우",
  "jdgmnInfo": [
    {
      "question": "진료기록부에 영상진단의 판독이 있었음을 알 수 있는 기재가 있다면 이는 진료기록부의 진료기록과 다르게 자동차보험 진료수가를 청구한 것이라고 할 수 없는가?",
      "answer": "불명"
    }
  ],
  "Summary": [
    {
      "summ_contxt": "의료기관이 보험사업자등에게 자동차보험 진료수가를 청구함에 있어서 영상진단 판독소견서를 작성·비치하지 않은 채 영상진단 판독료를 청구한 행위가 법 제11조 제3항에 위반하는 것으로 되어 법 제38조 제3항에 의하여 처벌되는지 여부에 관하여 보면, 우선 판독소견서를 작성·비치하지 아니하고 진료기록부에도 영상진단에 관한 판독이 있었음을 알 수 있는 기재가 없는 등 판독에 관한 근거가 전혀 없음에도 판독료를 청구하였다면 이는 법 제11조 제3항을 위반한 행위에 해당할 것이지만, 만일 별도로 판독소견서를 작성·비치하지는 아니하였더라도 진료기록부에 영상진단에 대한 판독소견이 기재되어 있거나 그 판독이 있었음을 알 수 있는 기재가 있는 때에는 이러한 기재를 무시한 채 단지 판독소견서를 작성·비치하지 아니하였다는 이유만으로 이러한 경우의 판독료 청구를 법 제11조 제3항을 위반한 것으로 취급하여 처벌하는 것은 법 제11조 제3항의 문언 자체에 반하는 것으로 허용될 수 없다고 보아야 한다.",
      "summ_pass": "이러한 경우의 판독료 청구를 법 제11조 제3항을 위반한 것으로 취급하여 처벌하는 것은 법 제11조 제3항의 문언 자체에 반하는 것으로 허용될 수 없다고 보아야 한다."
    }
  ],
  "keyword_tagg": [
    {
      "id": 1,
      "keyword": "판독소견서"
    },
    {
      "id": 2,
      "keyword": "진료기록부"
    }
  ],
  "Reference_info": {
    "reference_rules": "자동차손해배상 보장법 제11조 제3항, 제38조 제3항",
    "reference_court_case": "대법원 2006. 7. 13. 선고 2006도2959 판결"
  },
  "Class_info": {
    "class_name": "형사B(일반형)",
    "instance_name": "자동차손해배상보장법"
  }
}