{
  "info": {
    "id": 42045858,
    "dataType": "판결문",
    "caseNm": "손해배상(의)",
    "caseTitle": "대법원 2010. 10. 14. 선고 2007다3162 판결",
    "courtType": "판례(대법원)",
    "courtNm": "대법원",
    "judmnAdjuDe": "2010-10-14",
    "caseNoID": "2007다3162",
    "caseNo": "2007다3162"
  },
  "jdgmn": "[1] 사람의 신체에서 분리된 세포가 구 약사법의 규제대상인 의약품에 해당하는지 여부(한정 적극)\n[2] 중간엽 줄기세포가 구 약사법의 규제를 받는 의약품에 해당한다고 본 사례\n[3] 구 약사법 제26조의4 제1항에 정한 ‘임상시험’의 의미\n[4] 사람을 대상으로 한 중간엽 줄기세포 이식술은 임상시험에 해당하므로 식품의약품안전청장의 승인을 얻지 않고 그 줄기세포를 이식하는 행위는 구 약사법에 위배된다고 한 사례\n[5] 감독관청의 승인 없이 임상시험에 해당하는 의료행위를 하였다는 것만으로 불법행위가 성립하는지 여부(소극)\n[6] 임상시험 단계의 의료행위에 대한 의사의 설명의무의 내용 및 임상시험 단계에 있는 의약품의 공급에 따른 의약품 공급자의 고지의무의 내용\n[7] 의사가 간경화증이 상당히 진행되어 간이식 수술 외에 효과적인 치료방법이 없는 상태의 환자 등에게 임상단계에 있는 중간엽 줄기세포 이식술을 시행하면서 줄기세포 공급업체 대표이사와의 기자회견 등을 통하여 그릇된 정보를 제공하는 등 환자들에 대한 설명의무를 위반한 잘못이 있고, 줄기세포 공급업체 대표이사 역시 임상시험 단계에 있는 줄기세포를 판매하면서 위 기자회견 등을 통하여 그릇된 정보를 제공하는 등 줄기세포 구입자들에 대한 설명의무 내지 고지의무를 위반한 잘못이 있으며, 위 대표이사와 의사의 불법행위는 서로 객관적 관련공동성이 있어 공동불법행위를 구성한다고 본 사례",
  "jdgmnInfo": [
    {
      "question": "사람의 신체에서 분리된 세포가 사람의 질병 치료를 목적으로 인체조직이 아닌 세포단위로 사용되는 경우에는 약사법 규정에 따른 의약품에 해당하므로 약사법의 규제대상이 되는가?",
      "answer": "긍정"
    }
  ],
  "Summary": [
    {
      "summ_contxt": "약사법은 의약품에 관하여 임상시험계획의 승인이나 제조품목허가의 권한을 식품의약품안전청장에게 부여하였을 뿐 의약품의 구체적 범위를 하위 법령으로 정하도록 위임하는 규정을 두고 있지 않으므로, 약사법의 규제를 받는 의약품인지 여부는 그 정의 규정인 약사법 제2조의 해석에 따라 판단하여야 하는바, 약사법은 제2조 제4항 제2호에서 ‘사람 또는 동물의 질병의 진단·치료·경감·처치 또는 예방의 목적으로 사용되는 물품으로서 기구·기계 또는 장치가 아닌 것’을 의약품의 하나로 규정하고 있고, 사람의 신체에서 분리된 세포가 사람의 질병 치료를 목적으로 인체조직이 아닌 세포단위로 사용되는 경우에는 위 규정에 따른 의약품에 해당하므로 약사법의 규제대상이 된다.",
      "summ_pass": "사람의 신체에서 분리된 세포가 사람의 질병 치료를 목적으로 인체조직이 아닌 세포단위로 사용되는 경우에는 약사법 규정에 따른 의약품에 해당하므로 약사법의 규제대상이 된다."
    }
  ],
  "keyword_tagg": [
    {
      "id": 1,
      "keyword": "약사법"
    },
    {
      "id": 2,
      "keyword": "의약품"
    }
  ],
  "Reference_info": {
    "reference_rules": "[1] 구 약사법(2007. 4. 11. 법률 제8365호로 전부 개정되기 전의 것) 제2조 제4항 제2호(현행 제2조 제4호 참조), 제26조(현행 제31조 참조), 제26조의4 제1항(현행 제34조 제1항 참조), 구 약사법 시행규칙(2004. 7. 28. 보건복지부령 제291호로 개정되기 전의 것) 제21조의2 제1호(현행 제22조 제1호 참조) [2] 구 약사법(2007. 4. 11 법률 제8365호로 전부 개정되기 전의 것) 제2조 제4항 제2호(현행 제2조 제4호 참조), 제26조(현행 제31조 참조), 제26조의4 제1항(현행 제34조 제1항 참조), 구 약사법 시행규칙(2004. 7. 28. 보건복지부령 제291호로 개정되기 전의 것) 제21조의2 제1호(현행 제22조 제1호 참조) [3] 구 약사법(2007. 4. 11 법률 제8365호로 전부 개정되기 전의 것) 제26조의4 제1항(현행 제34조 제1항 참조) [4] 구 약사법(2007. 4. 11 법률 제8365호로 전부 개정되기 전의 것) 제26조의4 제1항(현행 제34조 제1항 참조) [5] 구 약사법(2007. 4. 11 법률 제8365호로 전부 개정되기 전의 것) 제26조의4 제1항(현행 제34조 제1항 참조) / 민법 제750조 [6] 민법 제2조, 제750조, 제760조 [7] 민법 제2조, 제750조, 제760조",
    "reference_court_case": "[5] 대법원 2002. 1. 11. 선고 2001다27449 판결(공2002상, 457) [6] 대법원 1995. 1. 20. 선고 94다3421 판결(공1995상, 885), 대법원 1995. 3. 28. 선고 93다62645 판결(공1995상, 1735), 대법원 2007. 6. 1. 선고 2005다5812, 5829, 5836 판결(공2007하, 972)"
  },
  "Class_info": {
    "class_name": "민사",
    "instance_name": "손해배상"
  }
}