{
  "info": {
    "id": 41027686,
    "dataType": "판결문",
    "caseNm": "과징금납부명령취소",
    "caseTitle": "대법원 2009. 6. 25. 선고 2008두17097 판결",
    "courtType": "판례(대법원)",
    "courtNm": "대법원",
    "judmnAdjuDe": "2009-06-25",
    "caseNoID": "2008두17097",
    "caseNo": "2008두17097"
  },
  "jdgmn": "세제 4개사가 담합행위의 기본적 원칙에 관한 합의는 없었지만 단일한 의사에 터잡아 동일한 목적을 수행하기 위하여 담합행위를 단절됨이 없이 계속 실행하였다면 전체적으로 1개의 부당한 공동행위로 볼 여지가 있음에도, 담합행위의 기본적 원칙에 관한 합의를 한 사실 등을 인정할 증거가 없다는 이유로 일련의 담합행위를 하나의 연속된 행위가 아니라 각각의 개별적인 담합행위로 본 원심판결을 파기한 사례",
  "jdgmnInfo": [
    {
      "question": "세제 4개사가 담합행위의 기본적 원칙에 관한 합의는 없었지만 단일한 의사에 터잡아 동일한 목적을 수행하기 위하여 담합행위를 단절됨이 없이 계속 실행하였다면 전체적으로 1개의 부당한 공동행위로 볼 여지가 있음에도, 담합행위의 기본적 원칙에 관한 합의를 한 사실 등을 인정할 증거가 없다는 이유로 일련의 담합행위를 하나의 연속된 행위가 아니라 각각의 개별적인 담합행위로 보는가?",
      "answer": "부정"
    }
  ],
  "Summary": [
    {
      "summ_contxt": "원심은, 채택 증거를 종합하여 그 판시와 같은 사실을 인정한 다음, 이 사건 각 담합행위가 1개의 부당한 공동행위로 되기 위하여는 부당한 공동행위의 기본적 원칙에 관한 합의가 반드시 존재하여야 한다는 전제하에, 원고를 포함한 세제 4사가 부당한 공동행위의 기본적 원칙에 관한 합의를 하였고 그 합의를 실행하는 과정에서 매년 구체적인 가격 결정 등을 위한 합의를 계속한 사실을 인정할 아무런 증거가 없으므로, 이 사건 각 담합행위는 하나의 연속된 행위가 아니라 각각의 개별적인 담합행위로 보아야 한다고 판단하였다.\n그러나 위 법리에 비추어 살펴보면, 부당한 공동행위의 기본적 원칙에 관한 합의가 없더라도 이 사건 각 담합행위가 단일한 의사에 기하여 동일한 목적을 수행하기 위한 것으로서 단절됨이 없이 계속 실행되어 왔다면 이를 하나의 부당한 공동행위로 볼 여지가 있으므로, 원심으로서는 위와 같은 사정이 있는지를 잘 살펴 이 사건 각 담합행위가 전체적으로 하나의 부당한 공동행위에 해당하는지 여부를 판단하였어야 함에도 불구하고, 이와 달리 원고를 포함한 세제 4사가 이 사건 각 담합행위의 기본적 원칙에 관한 합의를 하였고 그 합의를 실행하는 과정에서 매년 구체적인 가격 결정 등을 위한 합의를 계속한 사실을 인정할 만한 증거가 없다는 이유로 위와 같이 판단하고 말았으니, 이러한 원심판결에는 부당한 공동행위의 개수에 관한 법리를 오해하여 판결에 영향을 미친 위법이 있고, 이를 지적하는 상고이유의 주장은 이유 있다.\n그러므로 원심판결을 파기하고, 사건을 다시 심리·판단하게 하기 위하여 원심법원으로 환송하기로 하여 관여 대법관의 일치된 의견으로 주문과 같이 판결한다.",
      "summ_pass": "부당한 공동행위의 기본적 원칙에 관한 합의가 없더라도 이 사건 각 담합행위가 단일한 의사에 기하여 동일한 목적을 수행하기 위한 것으로서 단절됨이 없이 계속 실행되어 왔다면 이를 하나의 부당한 공동행위로 볼 여지가 있다."
    }
  ],
  "keyword_tagg": [
    {
      "id": 1,
      "keyword": "부당한 공동행위"
    },
    {
      "id": 2,
      "keyword": "연속된 행위"
    }
  ],
  "Reference_info": {
    "reference_rules": "독점규제 및 공정거래에 관한 법률 제19조 제1항",
    "reference_court_case": "대법원 2008. 9. 25. 선고 2007두3756 판결(공2008하, 1468), 대법원 2009. 1. 30. 선고 2008두16179 판결"
  },
  "Class_info": {
    "class_name": "행정",
    "instance_name": "행정처분취소"
  }
}