{
  "info": {
    "id": 41029523,
    "dataType": "판결문",
    "caseNm": "하수도원인자부담금부과처분무효확인",
    "caseTitle": "대법원 2014. 11. 27. 선고 2014두38866 판결",
    "courtType": "판례(대법원)",
    "courtNm": "대법원",
    "judmnAdjuDe": "2014-11-27",
    "caseNoID": "2014두38866",
    "caseNo": "2014두38866"
  },
  "jdgmn": "[1] 도시개발사업의 사업시행자가 구 하수도법상 ‘타행위’에 해당하는 사업으로 조성한 토지에 그 사업계획에서 정해진 규모 및 용도에 따라 건축물이 건축된 경우, 사업시행자와 건축물 소유자 중 구 하수도법 제32조 제2항에서 정한 하수도원인자부담금을 부담하는 자\n[2] 관할 구청장이 토지구획정리사업으로 조성된 부지를 분양받아 건축물을 신축한 건축물 소유자 甲 등에게 하수도원인자부담금을 부과한 사안에서, 구 하수도법 제32조 제2항 등에 의해 타행위에 해당하는 위 사업으로 발생할 것이 예상되는 하수를 처리하는 데 필요한 공공하수도 설치에 소요되는 비용에 대하여는 그 원인을 조성한 사업시행자에게 부과한다는 하수도원인자부담금 부과 요건의 의미가 분명함에도, 구청장이 합리적인 근거 없이 그 의미를 잘못 해석하여 처분 요건이 충족되지 않은 상태에서 甲 등에게 한 위 부과처분은 하자가 중대하고 명백하다고 한 사례",
  "jdgmnInfo": [
    {
      "question": "구청장이 합리적인 근거 없이 그 의미를 잘못 해석하여 처분 요건이 충족되지 않은 상태에서 甲 등에게 한 위 부과처분은 하자가 중대한가?",
      "answer": "긍정"
    }
  ],
  "Summary": [
    {
      "summ_contxt": "하자 있는 행정처분이 당연무효가 되기 위해서는 그 하자가 법규의 중요한 부분을 위반한 중대한 것으로서 객관적으로 명백한 것이어야 하며, 하자가 중대하고 명백한지 여부를 판별함에 있어서는 그 법규의 목적, 의미, 기능 등을 목적론적으로 고찰함과 동시에 구체적 사안 자체의 특수성에 관하여도 합리적으로 고찰함을 요한다(대법원 1995. 7. 11. 선고 94누4615 전원합의체 판결, 대법원 2012. 2. 16. 선고 2010두10907 전원합의체 판결 등 참조). 그리고 행정청이 법령 규정의 문언상 처분 요건의 의미가 분명함에도 합리적인 근거 없이 그 의미를 잘못 해석한 결과, 처분 요건이 충족되지 아니한 상태에서 해당 처분을 한 경우에는 법리가 명백히 밝혀지지 아니하여 그 해석에 다툼의 여지가 있다고 볼 수는 없다(대법원 2014. 5. 16. 선고 2011두27094 판결 참조). 가사 인천광역시 의회가 위와 같은 구 조례의 개정 및 부칙 조항과 이 사건 조례 조항으로 이 사건 사업과 같은 토지구획정리사업의 시행자에게 하수도원인자부담금을 부담시키지 않으려는 의도에서 타행위인 도시의 개발사업에서 토지구획정리사업의 근거 법령을 제외한 것이라고 하더라도, 이로써 피고는 토지구획정리사업의 시행자에게 하수도원인자부담금을 부담시킬 수 없게 될 뿐이지 이를 이유로 공공하수도 확대의 실질적 원인자가 아닌 그 사업지구 내 부지를 분양받아 원래 사업에서 예정된 범위 내의 건축물을 신축한 원고들에게 하수도원인자부담금을 부담시킬 수 있는 것이 아님은 앞서 본 법리상 분명하므로, 하수도원인자부담금을 원고들에게 부과한 이 사건 처분의 하자가 중대하고도 명백한 것은 마찬가지이다. 그럼에도 원심이 그 판시와 같은 이유만으로 이 사건 각 처분에 하자가 있더라도 그 하자가 명백하여 당연무효라고 보기 어렵다고 판단한 데에는 행정처분의 당연무효에 관한 법리를 오해한 위법이 있고, 이 점을 지적하는 상고이유 주장은 이유 있다.",
      "summ_pass": "이 사건 사업과 같은 토지구획정리사업의 시행자에게 하수도원인자부담금을 부담시키지 않으려는 의도를 이유로 공공하수도 확대의 실질적 원인자가 아닌 그 사업지구 내 부지를 분양받아 원래 사업에서 예정된 범위 내의 건축물을 신축한 원고들에게 하수도원인자부담금을 부담시킬 수 있는 것이 아님은 앞서 본 법리상 분명하므로, 하수도원인자부담금을 원고들에게 부과한 이 사건 처분의 하자가 중대하고도 명백한 것은 마찬가지이다."
    }
  ],
  "keyword_tagg": [
    {
      "id": 1,
      "keyword": "하자 있는 행정처분"
    },
    {
      "id": 2,
      "keyword": "법리 오해"
    }
  ],
  "Reference_info": {
    "reference_rules": "[1] 구 하수도법(2006. 9. 27. 법률 제8014호로 전부 개정되기 전의 것) 제32조 제2항(현행 제61조 제2항 참조) [2] 구 하수도법(2006. 9. 27. 법률 제8014호로 전부 개정되기 전의 것) 제32조 제2항(현행 제61조 제2항 참조), 행정소송법 제19조",
    "reference_court_case": "[1] 대법원 2004. 9. 24. 선고 2003두6849 판결(공2004하, 1748), 대법원 2008. 3. 20. 선고 2007두6342 전원합의체 판결(공2008상, 593)"
  },
  "Class_info": {
    "class_name": "행정",
    "instance_name": "행정처분취소"
  }
}