{
  "info": {
    "id": 44035226,
    "dataType": "판결문",
    "caseNm": "자동차운전면허 취소처분 취소청구",
    "caseTitle": "국민권익위원회 2015-6533, 2015. 7. 21.",
    "courtType": "심결례",
    "courtNm": "국민권익위원회",
    "judmnAdjuDe": "2015-07-21",
    "caseNoID": "2015-6533",
    "caseNo": "2015-6533"
  },
  "jdgmn": "",
  "jdgmnInfo": [
    {
      "question": "강제보험 미가입 자동차를 운행하는 경우에 성립하는 자동차손해배상보장법의 주체가 자동차의 등록명의자에 국한되는가?",
      "answer": "부정"
    }
  ],
  "Summary": [
    {
      "summ_contxt": "청구인이 2015. 3. 13. 혈중알코올농도 0.122%의 술에 취한 상태에서 운전했다는 이유로 피청구인이 2015. 3. 24. 청구인의 운전면허를 취소(이하 ‘이 사건 처분’이라 한다)하였다. 청구인은 이 사건 당시 유치원 운전기사이던 자로서 1992. 5. 18. 제2종 보통운전면허를 취득하여 2000. 1. 30. 음주운전으로 운전면허가 취소되어 2001. 3. 22. 제2종 보통운전면허를 취득하였는데, 최초로 운전면허를 취득한 이래 1회의 교통사고전력(1999. 12. 18. 물적 피해·음주운전)이 있고, 교통법규위반전력은 없다. 청구인이 운전면허취소기준치를 넘어 술에 취한 상태에서 자동차를 운전한 사실은 인정되나, 최근 14년 1개월 동안 사고 없이 운전한 점, 이 사건 음주운전으로 피해가 발생하지 않은 점 등을 고려할 때 이 사건 처분은 다소 가혹하므로 제1종 대형, 제2종 보통 운전면허 취소처분을 110일의 제1종 대형, 제1종 보통 운전면허 정지처분으로 변경한다.",
      "summ_pass": "위 인정사실에 따르면 청구인은 운전면허취소기준치를 넘어 술에 취한 상태에서 자동차를 운전한 사실은 인정되나, 최근 14년 1개월 동안 사고 없이 운전한 점, 이 사건 음주운전으로 피해가 발생하지 않은 점 등을 고려할 때 이 사건 처분은 다소 가혹하다."
    }
  ],
  "keyword_tagg": [
    {
      "id": 1,
      "keyword": "음주운전"
    },
    {
      "id": 2,
      "keyword": "음주운전으로 운전면허가 취소"
    }
  ],
  "Reference_info": {
    "reference_rules": "도로교통법 제93조제1항제1호 도로교통법 시행규칙 제91조제1항, 별표 28 중 2. 취소처분 개별기준 일련번호란 2",
    "reference_court_case": ""
  },
  "Class_info": {
    "class_name": "행정",
    "instance_name": "행정처분취소"
  }
}