{
  "info": {
    "id": 42046106,
    "dataType": "판결문",
    "caseNm": "부당이득금(과세처분의 당연무효 인정기준 사건)",
    "caseTitle": "대법원 2018. 7. 19. 선고 2017다242409 전원합의체 판결",
    "courtType": "판례(대법원)",
    "courtNm": "대법원",
    "judmnAdjuDe": "2018-07-19",
    "caseNoID": "2017다242409",
    "caseNo": "2017다242409"
  },
  "jdgmn": "[1] 과세처분이 당연무효라고 하기 위한 요건 및 과세처분의 하자가 중대하고 명백한지 판별하는 방법 / 어느 법률관계나 사실관계에 대하여 어느 법령의 규정을 적용할 수 없다는 법리가 명백히 밝혀지지 않아 해석에 다툼의 여지가 있는 상태에서 과세관청이 이를 잘못 해석하여 과세처분을 한 경우, 그 하자가 명백하다고 할 수 있는지 여부(소극)\n[2] 납세자가 조세환급금에 대하여 이행청구를 한 이후에는 환급가산금청구권과 지연손해금청구권이 경합적으로 발생하는지 여부(적극)",
  "jdgmnInfo": [
    {
      "question": "납세자가 조세환급금에 대하여 이행청구를 한 이후에는 환급가산금청구권과 지연손해금청구권이 경합적으로 발생하는가?",
      "answer": "긍정"
    }
  ],
  "Summary": [
    {
      "summ_contxt": "조세환급금은 조세채무가 처음부터 존재하지 않거나 그 후 소멸하였음에도 불구하고 국가가 법률상 원인 없이 수령하거나 보유하고 있는 부당이득에 해당하고, 환급가산금은 그 부당이득에 대한 법정이자로서의 성질을 가진다. 부당이득반환의무는 일반적으로 기한의 정함이 없는 채무로서, 수익자는 이행청구를 받은 다음 날부터 이행지체로 인한 지연손해금을 배상할 책임이 있다. 그러므로 납세자가 조세환급금에 대하여 이행청구를 한 이후에는 법정이자의 성질을 가지는 환급가산금청구권 및 이행지체로 인한 지연손해금청구권이 경합적으로 발생하고, 납세자는 자신의 선택에 좇아 그중 하나의 청구권을 행사할 수 있다.",
      "summ_pass": "조세환급금은 조세채무가 처음부터 존재하지 않거나 그 후 소멸하였음에도 불구하고 국가가 법률상 원인 없이 수령하거나 보유하고 있는 부당이득에 해당하고, 환급가산금은 그 부당이득에 대한 법정이자로서의 성질을 가진다."
    }
  ],
  "keyword_tagg": [
    {
      "id": 1,
      "keyword": "환급가산금"
    },
    {
      "id": 2,
      "keyword": "조세채무"
    },
    {
      "id": 3,
      "keyword": "조세환급금"
    },
    {
      "id": 4,
      "keyword": "법정이자"
    }
  ],
  "Reference_info": {
    "reference_rules": "[1] 국세기본법 제51조 / 민법 제741조 [2] 국세기본법 제51조, 제52조 / 민법 제387조 제2항, 제390조, 제397조 제1항, 제741조, 제748조",
    "reference_court_case": "[1] 대법원 2008. 3. 27. 선고 2006다1633 판결(공2008상, 603), 대법원 2013. 12. 26. 선고 2011다103809 판결 [2] 대법원 2009. 9. 10. 선고 2009다11808 판결(공2009하, 1627)"
  },
  "Class_info": {
    "class_name": "민사",
    "instance_name": "부당이득금"
  }
}