{
  "info": {
    "id": 43002555,
    "dataType": "판결문",
    "caseNm": "특정경제범죄가중처벌등에관한법률위반(사기)·사문서위조·위조사문서행사",
    "caseTitle": "대법원 2017. 9. 26. 선고 2017도8449 판결",
    "courtType": "판례(대법원)",
    "courtNm": "대법원",
    "judmnAdjuDe": "2017-09-26",
    "caseNoID": "2017도8449",
    "caseNo": "2017도8449"
  },
  "jdgmn": "사기죄의 성립요건 / 사기죄의 피해자가 법인이나 단체인 경우, 기망행위로 인한 착오, 인과관계 등이 있었는지 판단하는 기준이 되는 자(=대표 등 최종 의사결정권자 또는 내부적인 권한 위임 등에 따라 실질적으로 법인의 의사를 결정하고 처분을 할 권한을 가지고 있는 사람) / 피해자 법인이나 단체의 대표자 또는 실질적으로 의사결정을 하는 최종결재권자 등이 기망행위자와 동일인이거나 기망행위자와 공모하는 등 기망행위임을 알고 있었던 경우, 사기죄가 성립하는지 여부(소극) / 피해자 법인이나 단체의 업무를 처리하는 실무자인 일반 직원이나 구성원 등이 기망행위임을 알고 있었으나, 그 대표자 또는 실질적으로 의사결정을 하는 최종결재권자 등이 기망행위임을 알지 못한 채 착오에 빠져 처분행위에 이른 경우, 피해자 법인에 대한 사기죄가 성립하는지 여부(적극)",
  "jdgmnInfo": [
    {
      "question": "피해자 법인·단체의 대표자 또는 실질적으로 의사결정을 하는 최종결재권자 등이 기망행위자이거나 기망행위자와 공모하는 등 기망행위임을 알고 있었던 경우, 사기죄가 성립하는지?",
      "answer": "부정"
    }
  ],
  "Summary": [
    {
      "summ_contxt": "피해자 법인이나 단체의 대표자 또는 실질적으로 의사결정을 하는 최종결재권자 등이 기망행위자와 동일인이거나 기망행위자와 공모하는 등 기망행위임을 알고 있었던 경우에는 기망행위로 인한 착오가 있다고 볼 수 없고, 재물 교부 등의 처분행위가 있었더라도 기망행위와 인과관계가 있다고 보기 어렵다. 이러한 경우에는 사안에 따라 업무상횡령죄 또는 업무상배임죄 등이 성립하는 것은 별론으로 하고 사기죄가 성립한다고 볼 수 없다.",
      "summ_pass": "피해자 법인·단체의 대표자 또는 최종결재권자 등이 기망행위자이거나 기망행위를 알고 있었던 경우에는 업무상횡령죄 또는 업무상배임죄 등이 성립하는 것은 별론으로 하고 사기죄는 성립하지 않는다."
    }
  ],
  "keyword_tagg": [
    {
      "id": 1,
      "keyword": "최종결재권자"
    },
    {
      "id": 2,
      "keyword": "기망행위"
    },
    {
      "id": 3,
      "keyword": "업무상횡령"
    },
    {
      "id": 4,
      "keyword": "업무상배임"
    },
    {
      "id": 5,
      "keyword": "사기"
    },
    {
      "id": 6,
      "keyword": "착오"
    },
    {
      "id": 7,
      "keyword": "인과관계"
    }
  ],
  "Reference_info": {
    "reference_rules": "형법 제347조, 제355조, 제356조",
    "reference_court_case": "대법원 2000. 6. 27. 선고 2000도1155 판결(공2000하, 1800), 대법원 2017. 8. 29. 선고 2016도18986 판결(공2017하, 1898)"
  },
  "Class_info": {
    "class_name": "형사B(일반형)",
    "instance_name": "특정경제범죄가중처벌"
  }
}