{
  "info": {
    "id": 53658399,
    "dataType": "판결문",
    "caseNm": "학교폭력 가해학생 조치처분 취소",
    "caseTitle": "수원지방법원 2022-11-17 선고 2022구합74196 판결",
    "courtType": "판례(하급심)",
    "courtNm": "수원지방법원",
    "judmnAdjuDe": "2022-11-17",
    "caseNoID": "2022구합74196",
    "caseNo": "2022구합74196"
  },
  "jdgmn": "",
  "jdgmnInfo": [
    {
      "question": "학교폭력예방법에 따른 특별 교육 이수 처분이 주어질 때, 정신적 피해를 입혔다고 판단되는 경우에도 해당 처분을 부과할 수 있는가?",
      "answer": "긍정"
    }
  ],
  "Summary": [
    {
      "summ_contxt": "피고는 E심의위원회(이하 ‘심의위원회’라 한다)의 심의를 거쳐 2021. 12. 14. 원고에게 ‘F 학생의 여성성에 관한 험담과 G 학생의 보청기 착용과 관련한 험담 행위는 F, G 학생에게 정신상의 피해가 발생한 행위로 ‘학교폭력’에 해당하는 것으로 판단한다.’는 이유로 학교폭력예방 및 대책에 관한 법률(이하 ‘학교폭력예방법’이라 한다) 제17조 제1항에 따라 학내외 전문가에 의한 특별 교육 이수(6시간) 처분을 하였다(이하 ‘이 사건 처분’이라 한다). 원고는 이 사건 처분에 불복하여 2017. 12. 31. 강원도교육행정심판위원회에 행정심판을 청구하였으나, 위 위원회는 2022. 5. 25. 원고의 청구를 기각하였다. 위 인정사실, 앞서 든 각 증거, 갑 제12, 13호증의 각 기재, 변론 전체의 취지에 의하여 인정되는 아래의 사정들을 종합하여 보면, 이 사건 처분이 원고에게 지나치게 가혹하여 재량권을 일탈·남용하였다고 보기도 어렵다. 원고의 이 부분 주장도 이유 없다. 그렇다면, 원고의 청구는 이유 없으므로 이를 기각하기로 하여 주문과 같이 판결한다.",
      "summ_pass": "피고는 E심의위원회의 심의를 거쳐 2021. 12. 14. 원고에게 ‘F 학생의 여성성에 관한 험담과 G 학생의 보청기 착용과 관련한 험담 행위는 F, G 학생에게 정신상의 피해가 발생한 행위로 ‘학교폭력’에 해당하는 것으로 판단한다.’는 이유로 학교폭력예방 및 대책에 관한 법률 제17조 제1항에 따라 학내외 전문가에 의한 특별 교육 이수 처분을 하였다."
    }
  ],
  "keyword_tagg": [
    {
      "id": 1,
      "keyword": "정신상의 피해"
    },
    {
      "id": 2,
      "keyword": "학교폭력"
    }
  ],
  "Reference_info": {
    "reference_rules": "",
    "reference_court_case": "대법원 1995. 4. 14. 선고 94다58148 판결"
  },
  "Class_info": {
    "class_name": "개인정보/ICT",
    "instance_name": "학교폭력 가"
  }
}