{
  "info": {
    "id": 50005466,
    "dataType": "판결문",
    "caseNm": "계엄법위반·폭력행위등처벌에관한법률위반·현주건조물방화예비(예비:특수공무집행방해)·집회및시위에관한법률위반",
    "caseTitle": "대법원 1983. 5. 23., 선고, 82도142, 판결",
    "courtType": "판례(대법원)",
    "courtNm": "대법원",
    "judmnAdjuDe": "1983-05-23",
    "caseNoID": "82도142",
    "caseNo": "82도142"
  },
  "jdgmn": "계엄의 해제와 계엄실시중의 포고령위반소위에 대한 가벌",
  "jdgmnInfo": [
    {
      "question": "비상계엄이 해제되었다 하더라도 계엄실시중의 계엄포고령위반 소위에 대한 형이 범죄 후 법령의 개폐로 폐지된 것에 해당한다고 볼 수 없는 것인가?",
      "answer": "긍정"
    }
  ],
  "Summary": [
    {
      "summ_contxt": "제1심 판결 거시의 증거에 의하면 1980.5.17자 계엄사령관의 계엄포고 제10호에 의거 비상계엄 사태하에서는 모든 정치적 목적의 집회 및 시위가 금지되고 정치목적이 아닌 집회 등도 관할계엄사령부에 신고하여야 함에도 불구하고 피고인이 원심 공동피고인 등과 공모하여 1981.1.18.17:00경부터 22:00경까지 서울 동대문구 휘경동 공소외인 집에서 1981.1.6자 서울특별시장의 전국연합노동조합 청계 피복지부에 대한 해산 명령에 따른 대응책을 논의하기 위한 불법집회를 개최한 사실을 인정하기에 충분하고 또 비상계엄이 해제되었다 하더라도 계엄실시중의 계엄포고령위반 소위에 대한 형이 범죄 후 법령의 개폐로 폐지된 것에 해당한다고 볼 수 없는 것이므로(당원 1982.9.14 선고 82도1847 판결 참조) 피고인의 위 소위를 계엄법위반죄로 의율처단한 제1심판결을 유지한 원심의 조치는 정당하고 거기에 소론과 같은 채증법칙 위반이나 법리오해의 위법이 없으므로 논지는 채용할 수 없다.",
      "summ_pass": "비상계엄이 해제되었다 하더라도 계엄실시중의 계엄포고령위반 소위에 대한 형이 범죄 후 법령의 개폐로 폐지된 것에 해당한다고 볼 수 없는 것이므로(당원 1982.9.14 선고 82도1847 판결 참조) 피고인의 위 소위를 계엄법위반죄로 의율처단한 제1심판결을 유지한 원심의 조치는 정당하고 거기에 소론과 같은 채증법칙 위반이나 법리오해의 위법이 없으므로 논지는 채용할 수 없다."
    }
  ],
  "keyword_tagg": [
    {
      "id": 1,
      "keyword": "법리오해의 위법"
    }
  ],
  "Reference_info": {
    "reference_rules": "형법 제1조 제2항, 형사소송법 제326조 제4호",
    "reference_court_case": "대법원 1982.9.14 선고 82도1847 판결"
  },
  "Class_info": {
    "class_name": "형사A(생활형)",
    "instance_name": "계엄법위반"
  }
}