{
  "info": {
    "id": 55337206,
    "dataType": "판결문",
    "caseNm": "상표등록무효",
    "caseTitle": "대법원 1985. 2. 26., 선고, 84후15, 판결",
    "courtType": "판례(대법원)",
    "courtNm": "대법원",
    "judmnAdjuDe": "1985-02-26",
    "caseNoID": "84후15",
    "caseNo": "84후15"
  },
  "jdgmn": "가. 등록상표와 인용상표가 모두 주지성을 획득한 경우, 위 등록상표에 관하여는 상표법 제9조 제1항 제9호의 적용이 배제되는지 여부\n나. 하나의 상표에서 두 개 이상의 칭호, 관념을 생각할 수 있는 경우 그 상표와 타상표와의 유부 판단기준",
  "jdgmnInfo": [
    {
      "question": "등록상표와 인용상표가 모두 주지성을 획득한 경우, 위 등록상표에 관하여는\n상표법 제9조 제1항 제9호의 적용이 배제되는가?",
      "answer": "부정"
    }
  ],
  "Summary": [
    {
      "summ_contxt": "이 사건 등록상표가 그 등록 이전부터 피심판청구인의 상표로서 일반에게 주지되어 있었다 하더라도 그것이 주지상표로서 인용상표 또는 그와 동일 또는 유사한 다른 상표의 등록을 저지하고, 그 등록을 무효케 하는 사유가 될 수는 있을지언정, 이 사건 등록상표에 관하여\n상표법 제9조 제1항 제9호의 적용을 배제 또는 면하게 하는 사유가 될 수는 없다.",
      "summ_pass": "이 사건 등록상표에 관하여\n상표법 제9조 제1항 제9호의 적용을 배제 또는 면하게 하는 사유가 될 수는 없다."
    }
  ],
  "keyword_tagg": [
    {
      "id": 1,
      "keyword": "상표등록무효"
    }
  ],
  "Reference_info": {
    "reference_rules": "상표법 제9조",
    "reference_court_case": "가。나.\n대법원 1984.11.13. 선고 83후67 판결, 1984.11.13. 선고 83후70 판결"
  },
  "Class_info": {
    "class_name": "특허/저작권",
    "instance_name": "상표등록무효"
  }
}