{
  "info": {
    "id": 38004062,
    "dataType": "판결문",
    "caseNm": "사기, 폭행",
    "caseTitle": "대법원 1987. 7. 21. 선고 87도968 판결",
    "courtType": "판례(대법원)",
    "courtNm": "대법원",
    "judmnAdjuDe": "1987-07-21",
    "caseNoID": "87도968",
    "caseNo": "87도968"
  },
  "jdgmn": "거짓말탐지기의 검사가 증거능력을 갖기 위한 요건 및 증거력",
  "jdgmnInfo": [
    {
      "question": "거짓말탐지기의 검사결과는 검사를 받는 사람의 진술의 신빙성을 가늠하는 정황증거로서의 기능을 하는데 그치는 것이라고 보아야 하는가?",
      "answer": "긍정"
    }
  ],
  "Summary": [
    {
      "summ_contxt": "거짓말탐지기의 검사는 그 기구의 성능, 조작기술 등에 있어 신뢰도가 극히 높다고 인정되고 그 검사자가 적격자이며, 검사를 받는 사람이 검사를 받음에 동의하였으며, 검사서가 검사자 자신이 실시한 검사의 방법, 경과 및 그 결과를 충실하게 기재하였다는 등의 전제조건이 증거에 의하여 확인되었을 경우에만 형사소송법 제313조 제2항에 의하여 이를 증거로 할 수 있는 것이고, 위와 같은 조건이 모두 충족되어 증거능력이 있는 경우에도 그 검사결과는 검사를 받는 사람의 진술의 신빙성을 가늠하는 정황증거로서의 기능을 하는데 그치는 것이다.",
      "summ_pass": "조건이 모두 충족되어 증거능력이 있는 경우에도 그 검사결과는 검사를 받는 사람의 진술의 신빙성을 가늠하는 정황증거로서의 기능을 하는데 그치는 것이다."
    }
  ],
  "keyword_tagg": [
    {
      "id": 1,
      "keyword": "증거능력"
    },
    {
      "id": 2,
      "keyword": "거짓말탐지기"
    }
  ],
  "Reference_info": {
    "reference_rules": "형사소송법 제307조",
    "reference_court_case": ""
  },
  "Class_info": {
    "class_name": "형사B(일반형)",
    "instance_name": "형사소송법"
  }
}