{
  "info": {
    "id": 54171938,
    "dataType": "판결문",
    "caseNm": "소유권이전등기말소등",
    "caseTitle": "대법원 1989. 6. 27. 선고 88다카9111 판결",
    "courtType": "판례(대법원)",
    "courtNm": "대법원",
    "judmnAdjuDe": "1989-06-27",
    "caseNoID": "88다카9111",
    "caseNo": "88다카9111"
  },
  "jdgmn": "채권자대위권에 관한 법리오해 또는 심리미진의 위법이 있다 하여 원심판결을 파기한 사례",
  "jdgmnInfo": [
    {
      "question": "채권자대위권에 관한 법리오해 또는 심리미진의 위법이 있다 하여 원심판결을 파기할 수 있는가?",
      "answer": "긍정"
    }
  ],
  "Summary": [
    {
      "summ_contxt": "갑이 을에 대한 말소등기청구권을 가지고 을을 대위하여 병에게 그 명의의 등기말소를 소구한 경우 갑이 을에 대하여 이미 등기말소를 명하는 승소확정판결을 받았다면 을에 대하여는 말소등기청구권을 가지고 있다고 보아야 하고 을이 병에 대하여 가지는 말소등기청구권을 대위행사하기 위한 피보전권리로 삼을 수 있다고 보아야 하므로 을에 대한 말소등기청구권만 가지고서는 대위권행사의 요건을 다 갖추지 못한 것이라면 갑의 이 부분 소를 각하할 것이고 대위권행사의 요건을 갖추었다면 나아가 을이 병에 대하여 말소등기청구권이 있는지 여부를 심리판단하여야 한다.",
      "summ_pass": "말소등기청구권을 가지고 있다고 보아야 하고 을이 병에 대하여 가지는 말소등기청구권을 대위행사하기 위한 피보전권리로 삼을 수 있다고 보아야 하므로 을에 대한 말소등기청구권만 가지고서는 대위권행사의 요건을 다 갖추지 못한 것이라면 갑의 이 부분 소를 각하할 것이고 대위권행사의 요건을 갖추었다면 나아가 을이 병에 대하여 말소등기청구권이 있는지 여부를 심리판단하여야 한다."
    }
  ],
  "keyword_tagg": [
    {
      "id": 1,
      "keyword": "소유권이전등기"
    }
  ],
  "Reference_info": {
    "reference_rules": "민법 제404조",
    "reference_court_case": "1988.6.14. 선고 87다카2753 판결"
  },
  "Class_info": {
    "class_name": "민사",
    "instance_name": "소유권이전등기말소"
  }
}