{
  "info": {
    "id": 41047489,
    "dataType": "판결문",
    "caseNm": "약속어음금",
    "caseTitle": "부산지방법원 1996. 5. 17. 선고 95나10522 판결：확정",
    "courtType": "판례(하급심)",
    "courtNm": "부산지방법원",
    "judmnAdjuDe": "1996-05-17",
    "caseNoID": "95나10522",
    "caseNo": "95나10522"
  },
  "jdgmn": "수취인 기재가 있는 어음을 배서에 의하지 않고 단순히 타에 교부한 경우, 어음상의 권리이전 여부(소극)",
  "jdgmnInfo": [
    {
      "question": "수취인 기재가 있는 어음을 배서에 의하지 않고 단순히 타에 교부한 경우에 어음상의 권리이전으로 볼 수 있는가?",
      "answer": "부정"
    }
  ],
  "Summary": [
    {
      "summ_contxt": "그 어음상의 권리가 지명채권 양도의 방법으로 이전되었다고 하더라도 그 대항요건을 갖추었다고 볼 아무런 증거도 없으므로, 결국 문명수는 적법하게 위 어음상의 권리를 취득하지 못한 것이 되고, 위와 같이 무권리자인 문명수로부터 위 어음을 배서양도받은 원고 또한 발행인인 피고에 대한 관계에서는 위 어음상의 권리를 적법하게 승계취득하였다고 볼 수는 없어 원고가 위 어음의 적법한 소지인이라는 추정은 이로써 번복되었다 할 것이다.",
      "summ_pass": "어음을 배서양도받은 원고 또한 발행인인 피고에 대한 관계에서는 위 어음상의 권리를 적법하게 승계취득하였다고 볼 수는 없어 원고가 위 어음의 적법한 소지인이라는 추정은 깨진다."
    }
  ],
  "keyword_tagg": [
    {
      "id": 1,
      "keyword": "채권 양도"
    },
    {
      "id": 2,
      "keyword": "지명채권"
    }
  ],
  "Reference_info": {
    "reference_rules": "어음법 제14조 제2항",
    "reference_court_case": ""
  },
  "Class_info": {
    "class_name": "민사",
    "instance_name": "약속어음금"
  }
}