{
  "info": {
    "id": 44046581,
    "dataType": "판결문",
    "caseNm": "건물철거등",
    "caseTitle": "대법원 1996. 4. 26. 선고 95다52864 판결",
    "courtType": "판례(대법원)",
    "courtNm": "대법원",
    "judmnAdjuDe": "1996-04-26",
    "caseNoID": "95다52864",
    "caseNo": "95다52864"
  },
  "jdgmn": "[1] 건물에 대한 저당권의 효력이 그 건물의 소유를 목적으로 한 지상권에도 미치는지 여부(적극) 및 그 건물 양도시 지상권도 함께 양도되는지 여부(적극)\n[2] 지료에 관한 약정을 등기하지 않은 경우, 토지소유자가 구 지상권자의 지료연체 사실을 지상권 양수인에게 대항할 수 있는지 여부(소극)\n[3] 법정지상권에 관한 지료가 결정되지 않은 경우, 토지소유자가 2년 이상 지료지급 지체를 이유로 지상권 소멸청구를 할 수 있는지 여부(소극)",
  "jdgmnInfo": [
    {
      "question": "건물에 대한 저당권의 효력이 그 건물의 소유를 목적으로 한 지상권에도 미치는가?",
      "answer": "긍정"
    }
  ],
  "Summary": [
    {
      "summ_contxt": "토지소유자인 원고가 위와 같은 특별한 사정에 대한 아무런 입증을 하지 아니하였음을 알 수 있으므로, 저당권에 기한 경매절차에서 이 사건 건물의 2층을 경락받은 소외 1이 위 건물만이 아니라 그에 종된 권리인 위 건물의 소유를 목적으로 한 법정지상권도 등기 없이 취득하였고, 또한 위 소외 1로부터 위 건물을 매수한 피고 1은 건물만이 아니라 위 법정지상권도 양수한 것이라고 한 원심의 인정판단은 모두 정당한 것으로 수긍이 가고, 거기에 소론과 같은 지상권에 관한 법리오해, 판단유탈, 이유모순, 심리미진 등의 위법이 없다.",
      "summ_pass": "저당권에 기한 경매절차에서 이 사건 건물의 2층을 경락받은 소외 1이 위 건물만이 아니라 그에 종된 권리인 위 건물의 소유를 목적으로 한 법정지상권도 등기 없이 취득하였고, 또한 위 소외 1로부터 위 건물을 매수한 피고 1은 건물만이 아니라 위 법정지상권도 양수한 것이라고 한 원심의 인정판단은 모두 정당하다."
    }
  ],
  "keyword_tagg": [
    {
      "id": 1,
      "keyword": "법정지상권"
    }
  ],
  "Reference_info": {
    "reference_rules": "[1] 민법 제100조 제2항, 제187조, 제279조, 제358조, 제366조, 제371조 [2] 부동산등기법 제136조 / 민법 제186조, 제366조 [3] 민법 제287조, 제366조",
    "reference_court_case": "[1] 대법원 1985. 2. 26. 선고 84다카1578, 1579 판결(공1985, 469), 대법원 1992. 7. 14. 선고 92다527 판결(공1992, 2391), 대법원 1993. 4. 13. 선고 92다24950 판결(공1993상, 1379), 대법원 1995. 8. 22. 선고 94다12722 판결(공1995하, 3232) [3] 대법원 1994. 12. 2. 선고 93다52297 판결(공1995상, 424)"
  },
  "Class_info": {
    "class_name": "민사",
    "instance_name": "건물철거"
  }
}