{
  "info": {
    "id": 41001307,
    "dataType": "판결문",
    "caseNm": "배당이의",
    "caseTitle": "청주지방법원충주지원 1996. 6. 21. 선고 96가합365 판결：확정",
    "courtType": "판례(하급심)",
    "courtNm": "청주지방법원충주지원",
    "judmnAdjuDe": "1996-06-21",
    "caseNoID": "96가합365",
    "caseNo": "96가합365"
  },
  "jdgmn": "채권계산서에 배당요구신청서라는 제목의 기재가 없거나 인지를 첩부하지 아니한 경우, 이를 적법한 배당요구로 볼 수 있는지 여부(적극)",
  "jdgmnInfo": [
    {
      "question": "채권계산서에 배당요구신청서라는 제목의 기재가 없거나 인지를 첩부하지 아니한 경우, 이를 적법한 배당요구로 볼 수 있는가?",
      "answer": "긍정"
    }
  ],
  "Summary": [
    {
      "summ_contxt": "민사소송법 제605조 제1항, 제2항에서 배당요구의 원인이라 함은 채권자가 채무자의 총재산으로부터 변제를 받을 수 있는 법률관계를 말하므로, 배당요구를 함에 있어서는 채무자에 대한 청구채권의 발생원인과 그 수액 등을 명시한 서면을 경매법원에 제출하면 족한바, 채무자, 배당요구채권자 기타 배당요구의 원인사실 및 수액 등을 특정하기에 충분한 정도의 내용을 기재한 채권계산서를 경락기일 이전에 경매법원에 제출하였다면, 이로써 적법한 방식에 의한 배당요구를 하였다고 봄이 상당하고, 그 채권계산서에 배당요구신청서라는 제목을 달지 않았다거나 소정의 인지를 첩부하지 아니하였다는 사정만 가지고 적법한 방식에 의한 배당요구를 하지 아니한 것으로 볼 수는 없다.",
      "summ_pass": "채무자, 배당요구채권자 기타 배당요구의 원인사실 및 수액 등을 특정하기에 충분한 정도의 내용을 기재한 채권계산서를 경락기일 이전에 경매법원에 제출하였다면, 이로써 적법한 방식에 의한 배당요구를 하였다고 봄이 상당하고, 그 채권계산서에 배당요구신청서라는 제목을 달지 않았다거나 소정의 인지를 첩부하지 아니하였다는 사정만 가지고 적법한 방식에 의한 배당요구를 하지 아니한 것으로 볼 수는 없다."
    }
  ],
  "keyword_tagg": [
    {
      "id": 1,
      "keyword": "배당요구채권자"
    },
    {
      "id": 2,
      "keyword": "채권계산서"
    }
  ],
  "Reference_info": {
    "reference_rules": "민사소송법 제605조 / 민사소송규칙 제121조의3, 제148조의3",
    "reference_court_case": ""
  },
  "Class_info": {
    "class_name": "기업",
    "instance_name": "배당이의"
  }
}