{
  "info": {
    "id": 41034253,
    "dataType": "판결문",
    "caseNm": "이주자택지지정",
    "caseTitle": "대법원 1997. 2. 11. 선고 96누14067 판결",
    "courtType": "판례(대법원)",
    "courtNm": "대법원",
    "judmnAdjuDe": "1997-02-11",
    "caseNoID": "96누14067",
    "caseNo": "96누14067"
  },
  "jdgmn": "[1] 행정심판청구서에 불비된 사항이 있는 경우 및 그 취지가 불명확한 경우의 처리 방법\n[2] 한국토지공사가 정한 ‘이주자택지의공급에관한예규’의 법적 성질(사무처리준칙)\n[3] 공공용지의취득및손실보상에관한특례법 소정의 이주대책 대상자로서의 가옥 소유자는 실질적인 처분권을 가진 자를 의미하는지 여부(적극)",
  "jdgmnInfo": [
    {
      "question": "공공용지의취득및손실보상에관한특례법 소정의 이주대책 대상자로서의 가옥 소유자는 실질적인 처분권을 가진 자를 의미하는가?",
      "answer": "긍정"
    }
  ],
  "Summary": [
    {
      "summ_contxt": "한국토지공사의 이주자택지의공급에관한예규에 구획 등의 지정고시일 현재 사업지구 내에 소재한 가옥 등의 소유자로 보상을 받은 자를 이주자택지의 공급대상자로 규정하고 있다거나, 가옥소유자의 확인은 건물등기부등본에 의한다고 규정하고 있다 하더라도, 공공용지의취득및손실보상에관한특례법 제5조 제1항, 제5항, 제8조 제1항의 각 규정 취지에 비추어, 그 소유자는 대외적인 소유권을 가진 자를 의미하는 것이 아니라 실질적인 처분권을 가진 자를 의미하는 것으로 봄이 정당하고, 또한 건물등기부등본 이외의 다른 신빙성 있는 자료에 의하여 그와 같은 실질적인 처분권이 있음의 입증을 배제하는 것도 아니다.",
      "summ_pass": "공공용지의취득및손실보상에관한특례법 제5조 제1항, 제5항, 제8조 제1항의 각 규정 취지에 비추어, 그 소유자는 대외적인 소유권을 가진 자를 의미하는 것이 아니라 실질적인 처분권을 가진 자를 의미하는 것으로 봄이 정당하고, 또한 건물등기부등본 이외의 다른 신빙성 있는 자료에 의하여 그와 같은 실질적인 처분권이 있음의 입증을 배제하는 것도 아니다."
    }
  ],
  "keyword_tagg": [
    {
      "id": 1,
      "keyword": "공공용지의취득및손실보상에관한특례법"
    },
    {
      "id": 2,
      "keyword": "한국토지공사"
    }
  ],
  "Reference_info": {
    "reference_rules": "[1] 행정심판법 제19조, 제23조 / 행정소송법 제18조 [2] 공공용지의취득및손실보상에관한특례법 제8조 [3] 공공용지의취득및손실보상에관한특례법 제5조 제1항, 제5항, 제8조 제1항",
    "reference_court_case": "[1] 대법원 1993. 6. 29. 선고 92누19194 판결(공1993하, 2166), 대법원 1995. 9. 5. 선고 94누16250 판결(공1995하, 3410), 대법원 1995. 11. 10. 선고 94누12852 판결(공1995하, 3931) [2] 대법원 1994. 2. 22. 선고 93누15120 판결(공1994상, 1114), 대법원 1996. 4. 23. 선고 95누16493 판결 [3] 대법원 1992. 4. 24. 선고 91누8692 판결(공1992, 1737)"
  },
  "Class_info": {
    "class_name": "행정",
    "instance_name": "행정처분취소"
  }
}