{
  "info": {
    "id": 44041676,
    "dataType": "판결문",
    "caseNm": "토지소유권이전등기말소",
    "caseTitle": "대법원 1997. 3. 11. 선고 96다47142 판결",
    "courtType": "판례(대법원)",
    "courtNm": "대법원",
    "judmnAdjuDe": "1997-03-11",
    "caseNoID": "96다47142",
    "caseNo": "96다47142"
  },
  "jdgmn": "[1] 진정명의 회복을 위한 소유권이전등기청구의 요건\n[2] 진정명의 회복을 위한 소유권이전등기절차이행을 구할 수 없다고 본 사례",
  "jdgmnInfo": [
    {
      "question": "진정한 등기명의의 회복을 위한 소유권이전등기청구는 자기 명의로 소유권을 표상하는 등기가 되어 있었거나 법률에 의하여 소유권을 취득한 진정한 소유자가 그 등기명의를 회복하기 위한 방법으로 소유권에 기하여 현재의 등기명의인을 상대로 진정한 등기명의의 회복을 원인으로 한 소유권이전등기절차의 이행을 구하는 것이라 할 수 있는가?",
      "answer": "긍정"
    }
  ],
  "Summary": [
    {
      "summ_contxt": "진정한 등기명의의 회복을 위한 소유권이전등기청구는 자기 명의로 소유권을 표상하는 등기가 되어 있었거나 법률에 의하여 소유권을 취득한 진정한 소유자가 그 등기명의를 회복하기 위한 방법으로 소유권에 기하여 현재의 등기명의인을 상대로 진정한 등기명의의 회복을 원인으로 한 소유권이전등기절차의 이행을 구하는 것이다.\n원인무효인 소유권보존등기의 명의인인 피고가 이를 시정하기 위하여 진정한 소유자에게 인감도장과 등기필증을 교부하여 경료된 갑 명의의 소유권이전등기는 실체적 권리관계에 부합하여 유효한 것이고, 그 후 피고가 그의 인감증명이 위임장 없이 발급된 것을 문제삼아 갑이 피고에게 다시 소유권이전등기를 하였다면 그 등기 역시 특별한 사정이 없는 한 유효한 것이므로, 갑의 상속인인 원고는 진정한 등기명의의 회복을 위한 소유권이전등기절차의 이행을 구할 수 있는 소유자가 아니라고 본다.",
      "summ_pass": "진정한 소유자에게 인감도장과 등기필증을 교부하여 경료된 갑 명의의 소유권이전등기는 실체적 권리관계에 부합하여 유효한 것이고, 그 후 피고가 그의 인감증명이 위임장 없이 발급된 것을 문제삼아 갑이 피고에게 다시 소유권이전등기를 하였다면 그 등기 역시 특별한 사정이 없는 한 유효한 것이므로, 갑의 상속인인 원고는 진정한 등기명의의 회복을 위한 소유권이전등기절차의 이행을 구할 수 있는 소유자가 아니라고 본다."
    }
  ],
  "keyword_tagg": [
    {
      "id": 1,
      "keyword": "소유권이전등기청구"
    },
    {
      "id": 2,
      "keyword": "소유권이전등기절차"
    }
  ],
  "Reference_info": {
    "reference_rules": "[1] 민법 제186조 [2] 민법 제186조",
    "reference_court_case": "[1][2] 대법원 1990. 12. 21. 선고 88다카20026 판결(공1991, 578), 대법원 1993. 2. 23. 선고 92다48970 판결(공1993상, 1072)"
  },
  "Class_info": {
    "class_name": "민사",
    "instance_name": "토지소유권이전등기말소"
  }
}