{
  "info": {
    "id": 41003184,
    "dataType": "판결문",
    "caseNm": "특정범죄가중처벌등에관한법률위반(도주차량)",
    "caseTitle": "대법원 1996. 4. 9. 선고 96도252 판결",
    "courtType": "판례(대법원)",
    "courtNm": "대법원",
    "judmnAdjuDe": "1996-04-09",
    "caseNoID": "96도252",
    "caseNo": "96도252"
  },
  "jdgmn": "[1] 특정범죄가중처벌등에관한법률 제5조의3 제1항 소정의 ‘피해자를 구호하는 등 도로교통법 제50조 제1항의 규정에 의한 조치를 취하지 아니하고 도주한 때’의 의미\n[2] 교통사고 후 피해자와 경찰서에 신고하러 가다가 음주운전이 발각될 것이 두려워 피해자가 경찰서에 들어간 후 그냥 돌아간 경우 위 [1]항의 ‘도주한 때’에 해당한다고 본 사례",
  "jdgmnInfo": [
    {
      "question": "교통사고 후 피해자와 경찰서에 신고하러 가다가 피해자가 경찰서에 들어간 후 그냥 돌아간 경우, 도주한 때에 해당하는가?",
      "answer": "긍정"
    }
  ],
  "Summary": [
    {
      "summ_contxt": "[1] 특정범죄가중처벌등에관한법률 제5조의3 제1항 소정의 ‘피해자를 구호하는 등 도로교통법 제50조 제1항의 규정에 의한 조치를 취하지 아니하고 도주한 때’라 함은 사고운전자가 사고로 인하여 피해자가 사상을 당한 사실을 인식하였음에도 불구하고 피해자를 구호하는 등 도로교통법 제50조 제1항에 규정된 의무를 이행하기 이전에 사고현장을 이탈하여 사고를 낸 사람이 누구인지를 쉽게 알 수 없는 상태를 초래하는 경우를 말한다. [2] 교통사고를 일으킨 후 피해자와 경찰서에 신고하러 가다가 음주운전이 발각될 것이 두려워 피해자가 경찰서에 들어간 후 그냥 돌아간 경우 피해자에게 피고인의 직업과 이름을 알려 주었다는 등의 여러 사정이 있었다 하더라도 피해자의 구호의무를 이행하지 아니하고 사고현장을 이탈하여 도주한 것으로 본 원심판결을 긍인한 사례.",
      "summ_pass": "교통사고를 일으킨 후 피해자와 경찰서에 신고하러 가다가 음주운전이 발각될 것이 두려워 피해자가 경찰서에 들어간 후 그냥 돌아간 경우 피해자에게 피고인의 직업과 이름을 알려 주었다는 등의 여러 사정이 있었다 하더라도 피해자의 구호의무를 이행하지 아니하고 사고현장을 이탈하여 도주한 것으로 본 원심판결을 긍인한 사례."
    }
  ],
  "keyword_tagg": [
    {
      "id": 1,
      "keyword": "특정범죄가중처벌등에관한법률"
    },
    {
      "id": 2,
      "keyword": "사고현장 이탈"
    }
  ],
  "Reference_info": {
    "reference_rules": "[1] 특정범죄가중처벌등에관한법률 제5조의3 제1항 / 도로교통법 제50조 제1항 [2] 특정범죄가중처벌등에관한법률 제5조의3 제1항 / 도로교통법 제50조 제1항",
    "reference_court_case": "[1] 대법원 1992. 4. 10. 선고 91도1831 판결(공1992, 1636), 대법원 1993. 6. 11. 선고 92도3437 판결(공1993하, 2066), 대법원 1994. 10. 21. 선고 94도2204 판결(공1994하, 3162), 대법원 1995. 11. 24. 선고 95도1680 판결(공1996상, 300)"
  },
  "Class_info": {
    "class_name": "형사B(일반형)",
    "instance_name": "행정처분"
  }
}