{
  "info": {
    "id": 44043005,
    "dataType": "판결문",
    "caseNm": "소유권이전등기",
    "caseTitle": "대법원 1999. 7. 9. 선고 97다7943 판결",
    "courtType": "판례(대법원)",
    "courtNm": "대법원",
    "judmnAdjuDe": "1999-07-09",
    "caseNoID": "97다7943",
    "caseNo": "97다7943"
  },
  "jdgmn": "지방자치단체가 철거에 대한 보상으로 토지를 분양하여 주기로 합의하였음에도 그 효력 발생에 필요한 조처를 취하지 아니함으로써 그 보상합의가 효력을 발생하지 못하게 한 불법행위를 저지른 경우, 그로 인한 소극적 손해 산정의 기준 시점(=보상합의에서 정한 이행기) 및 이와 같이 산정된 손해가 통상손해인지 여부(적극)",
  "jdgmnInfo": [
    {
      "question": "지방자치단체가 철거에 대한 보상으로 토지를 분양하여 주기로 합의하였음에도 그 효력 발생에 필요한 조처를 취하지 아니함으로써 그 보상합의가 효력을 발생하지 못하게 한 불법행위를 저지른 경우, 그로 인한 소극적 손해 산정의 기준 시점은 무엇인가?",
      "answer": "불명"
    },
    {
      "question": "지방자치단체가 철거에 대한 보상으로 토지를 분양하여 주기로 합의하였음에도 그 효력 발생에 필요한 조처를 취하지 아니함으로써 그 보상합의가 효력을 발생하지 못하게 한 불법행위를 저지른 경우, 그로 인해 산정된 손해는 통상손해인가?",
      "answer": "긍정"
    }
  ],
  "Summary": [
    {
      "summ_contxt": "지방자치단체가 철거에 대한 보상으로 토지를 분양하여 주기로 합의하였음에도 그 효력 발생에 필요한 조처를 취하지 아니하여 그 보상합의가 효력을 발생하지 못하게 한 불법행위를 저질렀다면, 그로 인한 소극적 손해는 보상합의가 법령상 요건을 제대로 갖추어 보상합의에 정해진 내용대로 토지를 분양받았으면 얻을 수 있던 이익을 얻지 못하게 된 것을 의미한다. 그러므로 손해액을 산정함에 있어 보상합의가 유효했으면 그 내용대로 토지의 분양이 이행되어야 할 시기에 있어 합리적으로 산정된 시가를 기준으로 해야 하고, 그렇게 산출된 손해액은 객관적으로 보아 예측이 가능한 것으로서 통상의 손해에 해당한다. 지방자치단체가 이를 알았거나 알 수 있었는지 여부로 배상범위가 달라지는 것이 아니다.",
      "summ_pass": "지방자치단체가 철거에 대한 보상으로 토지를 분양하여 주기로 합의했으나 그 효력 발생에 필요한 조처를 취하지 않아서 보상합의가 효력을 발생하지 못하게 한 불법행위를 저지른 경우, 그로 인한 소극적 손해는 보상합의가 정해진 내용대로 토지를 분양받았으면 얻을 이익을 얻지 못하게 된 것이므로 손해액을 산정함에 보상합의가 유효했으면 토지의 분양이 이행되어야 할 시기에 합리적으로 산정된 시가를 기준으로 하고, 그렇게 산출된 손해액은 객관적으로 예측이 가능한 것으로서 통상의 손해에 해당한다."
    }
  ],
  "keyword_tagg": [
    {
      "id": 1,
      "keyword": "보상합의"
    },
    {
      "id": 2,
      "keyword": "불법행위"
    },
    {
      "id": 3,
      "keyword": "소극적 손해"
    }
  ],
  "Reference_info": {
    "reference_rules": "민법 제393조, 제750조, 제763조",
    "reference_court_case": "대법원 1992. 6. 23. 선고 91다33070 전원합의체 판결(공1992, 2235), 대법원 1996. 2. 9. 선고 94다53372 판결(공1996상, 884), 대법원 1998. 7. 10. 선고 96다38971 판결(공1998하, 2054)"
  },
  "Class_info": {
    "class_name": "민사",
    "instance_name": "소유권이전등기"
  }
}