{
  "info": {
    "id": 41017679,
    "dataType": "판결문",
    "caseNm": "총포·도검·화약류등단속법위반",
    "caseTitle": "대법원 1999. 12. 10. 선고 99도577 판결",
    "courtType": "판례(대법원)",
    "courtNm": "대법원",
    "judmnAdjuDe": "1999-12-10",
    "caseNoID": "99도577",
    "caseNo": "99도577"
  },
  "jdgmn": "[1] 공소권의 남용으로 공소제기의 효력이 부인되는 검사의 자의적인 공소권 행사의 의미\n[2] 검사가 구속영장기재의 범죄사실(선행사건)로 피고인을 신문할 당시 피고인이 여죄의 사실(후행사건)도 자백하였으나 검찰에 송치되지 아니하여 선행사건만을 먼저 기소한 후 그 판결 확정 후에 후행사건을 기소한 경우, 공소권 남용에 해당하지 않는다고 한 사례",
  "jdgmnInfo": [
    {
      "question": "검사가 구속영장기재의 범죄사실(선행사건)로 피고인을 신문할 당시 피고인이 여죄의 사실(후행사건)도 자백하였으나 검찰에 송치되지 아니하여 선행사건만을 먼저 기소한 후 그 판결 확정 후에 후행사건을 기소한 경우, 공소권 남용에 해당하는가?",
      "answer": "부정"
    }
  ],
  "Summary": [
    {
      "summ_contxt": "[1] 검사가 자의적으로 공소권을 행사하여 피고인에게 실질적인 불이익을 줌으로써 소추재량권을 현저히 일탈하였다고 보여지는 경우에 이를 공소권의 남용으로 보아 공소제기의 효력을 부인할 수 있는 것이고, 여기서 자의적인 공소권의 행사라 함은 단순히 직무상의 과실에 의한 것만으로는 부족하고 적어도 미필적이나마 어떤 의도가 있어야 한다. [2] 검사가 구속영장기재의 범죄사실(선행사건)로 피고인을 신문할 당시 피고인이 여죄의 사실(후행사건)도 자백하였으나 경찰에서 후행사건의 수사관계로 선행사건과 분리하여 뒤늦게 따로 송치한 관계로 선행사건의 기소 당시에는 후행사건은 검찰에 송치되기 전이었고 불구속으로 송치된 후행사건에 대하여 검사가 제1회 피의자신문을 할 당시 선행사건의 유죄판결이 의외로 빨리 확정된 경우, 검사의 후행사건에 대한 기소가 공소권 남용에 해당하지 않는다.",
      "summ_pass": "검사가 자의적으로 공소권을 행사하여 피고인에게 실질적인 불이익을 줌으로써 소추재량권을 현저히 일탈하였다고 보여지는 경우에 이를 공소권의 남용으로 보아 공소제기의 효력을 부인할 수 있는 것이고, 여기서 자의적인 공소권의 행사라 함은 단순히 직무상의 과실에 의한 것만으로는 부족하고 적어도 미필적이나마 어떤 의도가 있어야 한다."
    }
  ],
  "keyword_tagg": [
    {
      "id": 1,
      "keyword": "직무상의 과실"
    },
    {
      "id": 2,
      "keyword": "공소권 남용"
    }
  ],
  "Reference_info": {
    "reference_rules": "[1] 형사소송법 제247조 [2] 형사소송법 제247조",
    "reference_court_case": "[2] 대법원 1996. 2. 13. 선고 94도2658 판결(공1996상, 1017), 대법원 1996. 9. 24. 선고 96도1730 판결(공1996하, 3264), 대법원 1997. 6. 27. 선고 97도508 판결(공1997하, 2424), 대법원 1998. 7. 10. 선고 98도1273 판결(공1998하, 2185)"
  },
  "Class_info": {
    "class_name": "형사A(생활형)",
    "instance_name": "행정처분"
  }
}