{
  "info": {
    "id": 42036120,
    "dataType": "판결문",
    "caseNm": "공동주택관리규약개정신고수리취소",
    "caseTitle": "국민권익위원회 서행심 2013-603, 2013. 9. 9.",
    "courtType": "심결례",
    "courtNm": "국민권익위원회",
    "judmnAdjuDe": "2013-09-09",
    "caseNoID": "서행심 2013-603",
    "caseNo": "서행심 2013-603"
  },
  "jdgmn": "",
  "jdgmnInfo": [
    {
      "question": "입주자 대표회의가 위 각 요건을 구비하여 피청구인에게 이 사건 규약의 개정신고를 한 것이므로 피청구인이 관련법에 따라 이 사건 입주자 대표회의에 대하여 위 신고를 수리한 것은 부당하다고 할 수 있는가?",
      "answer": "부정"
    }
  ],
  "Summary": [
    {
      "summ_contxt": "「임대주택법」에서는 임대주택이 아닌 주택과 임대주택이 같은 건축물 안에 있거나 같은 주택단지를 구성하는 혼합단지의 경우 임대주택이 아닌 주택의 관리방법을 따라야 함을 규정하고 있다. 이 사건 처분에 관하여 본다. 「주택법」에서는 공동주택의 입주자와 사용자로 하여금 시에서 정하는 관리규약 준칙의 내용을 참조하여 관리규약을 정하도록 규정하고 있고 위 인정사실 및 답변서 등 관련 자료에 의하면, 이 사건 규약의 경우 2013. 3. 9. 개정된 「서울특별시 공동주택 관리규약 준칙」에 따라 내용을 변경한 것이고 「주택법 시행령」을 따라 ○○○○○ 마고정 11단지 전체 입주자 등의 과반수가 찬성함으로써 그 절차적 요건도 충족하였는바, 이 사건 입주자 대표회의가 위 각 요건을 구비하여 피청구인에게 이 사건 규약의 개정신고를 한 것이므로, 피청구인이 관련법에 따라 이 사건 입주자 대표회의에 대하여 위 신고를 수리한 것은 위법하거나 부당하다고 할 수 없다.",
      "summ_pass": "공동주택 관리규약 준칙에 따라 내용을 변경한 것이고 「주택법 시행령」을 따라 ○○○○○ 마고정 11단지 전체 입주자 등의 과반수가 찬성함으로써 그 절차적 요건도 충족하였는바, 이 사건 입주자 대표회의가 위 각 요건을 구비하여 피청구인에게 이 사건 규약의 개정신고를 한 것이므로, 피청구인이 관련법에 따라 이 사건 입주자 대표회의에 대하여 위 신고를 수리한 것은 위법하거나 부당하다고 할 수 없다."
    }
  ],
  "keyword_tagg": [
    {
      "id": 1,
      "keyword": "공동주택"
    }
  ],
  "Reference_info": {
    "reference_rules": "주택법 제44조 주택법 시행령 제52조, 제57조 서울시 공동주택 관리규약 적용지침 제6호 임대주택법 제28조 제6항",
    "reference_court_case": ""
  },
  "Class_info": {
    "class_name": "행정",
    "instance_name": "행정처분취소"
  }
}