{
  "info": {
    "id": 38019865,
    "dataType": "판결문",
    "caseNm": "일반음식점영업정지처분취소",
    "caseTitle": "국민권익위원회 서행심2013-624, 2013. 8. 26.",
    "courtType": "심결례",
    "courtNm": "국민권익위원회",
    "judmnAdjuDe": "2013-08-26",
    "caseNoID": "서행심2013-624",
    "caseNo": "서행심2013-624"
  },
  "jdgmn": "",
  "jdgmnInfo": [
    {
      "question": "식품위생법에 따라서 청소년에게 주류를 제공하였을 경우 1차 위반 시 영업정지 2개월의 행정처분이 부과됨이 적법한가?",
      "answer": "긍정"
    }
  ],
  "Summary": [
    {
      "summ_contxt": "가) 「식품위생법」 제44조 및 제75조의 규정에 의하면, 식품접객영업자는 「청소년 보호법」 제2조에 따른 청소년에게 주류를 제공하는 행위를 하여서는 아니 되고 이를 위반할 경우 영업허가 또는 등록을 취소하거나 6개월 이내의 기간을 정하여 그 영업의 전부 또는 일부를 정지하거나 영업소 폐쇄를 명할 수 있다고 되어 있으며, 같은 법 시행규칙 제89조 별표 23에 의하면 청소년에게 주류를 제공하였을 경우 1차 위반 시 영업정지 2개월의 행정처분을 규정하고 있다.\n나) 이 사건 처분에 관하여 본다.\n위 인정 사실 및 서울송파경찰서 수사기록 등에 의하면 청구인은 2012. 8. 14. 사건 당시 청소년에게 주류를 제공함으로써 위 법을 위반한 사실이 인정되는바 그 외에 청구인에게 이 사건 처분을 감경할 만한 다른 특별한 사유가 있다고 할 수 없으므로 피청구인이 관련 법령에서 정한 절차에 따라 청구인에게 한 이 사건 처분은 위법하다거나 부당하다고 할 수 없다.",
      "summ_pass": "청구인에게 이 사건 처분을 감경할 만한 다른 특별한 사유가 있다고 할 수 없으므로 피청구인이 관련 법령에서 정한 절차에 따라 청구인에게 한 이 사건 처분은 위법하다거나 부당하다고 할 수 없다."
    }
  ],
  "keyword_tagg": [
    {
      "id": 1,
      "keyword": "청소년에게 주류 제공"
    },
    {
      "id": 2,
      "keyword": "식품접객영업자"
    }
  ],
  "Reference_info": {
    "reference_rules": "식품위생법 제44조, 제75조 식품위생법 시행규칙 제89조 별표 23",
    "reference_court_case": ""
  },
  "Class_info": {
    "class_name": "행정",
    "instance_name": "영업정지/영업허가"
  }
}