{
  "info": {
    "id": 42035701,
    "dataType": "판결문",
    "caseNm": "건설업 부실벌점 부과처분 취소청구",
    "caseTitle": "국민권익위원회 중앙행심2012-02517, 2013. 1. 22.",
    "courtType": "심결례",
    "courtNm": "국민권익위원회",
    "judmnAdjuDe": "2013-01-22",
    "caseNoID": "중앙행심2012-02517",
    "caseNo": "중앙행심2012-02517"
  },
  "jdgmn": "",
  "jdgmnInfo": [
    {
      "question": "청구인들이 기존관을 교체하도록 계획되어 있는 팔복급수구역 중 일부구간을 미시공한 채 준공처리한 것을 확인하고 피청구인이 청구인들에게 각 2점의 부실벌점을 부과한 처분은 적법, 타당한가요?",
      "answer": "긍정"
    }
  ],
  "Summary": [
    {
      "summ_contxt": "건설업자가 기존 관로를 교체·신설·갱생하는 공사를 하면서 기존관을 교체하도록 계획되어 있는 이 사건 구간에 기존관이 그대로 설치되어 있음에도 이를 준공처리하여 「건설기술관리법」상 설계도서 및 관련 기준대로 시공하여야 할 의무를 위반하였음을 이유로 부실벌점이 부과된 사안에서, 행정법규 위반에 대하여 가하는 제재조치는 행정목적의 달성을 위하여 행정법규 위반이라는 객관적 사실에 착안하여 가하는 제재이므로 위반자의 의무 해태를 탓할 수 없는 정당한 사유가 있는 등의 특별한 사정이 없는 한 위반자에게 고의나 과실이 없다고 하더라도 부과될 수 있는 것으로, 공사의 하도급 업체가 금원편취 목적으로 고의적으로 부실공사 등을 하여 형사처벌을 받은 사실이 있고, 기존관 사용에 크게 문제가 없다고 하더라도 그러한 사실만으로 청구인들의 의무 해태를 탓할 수 없는 정당한 사유가 있다고 할 수는 없다.",
      "summ_pass": "행정법규 위반에 대하여 가하는 제재조치는 행정법규 위반이라는 객관적 사실에 착안하여 가하는 제재이므로 특별한 사정이 없는 한 위반자에게 고의나 과실이 없다고 하더라도 부과될 수 있는 것으로, 공사의 하도급 업체가 금원편취 목적으로 고의적으로 부실공사 등을 하여 형사처벌을 받은 사실이 있고, 기존관 사용에 크게 문제가 없다고 하더라도 그러한 사실만으로 청구인들의 의무 해태를 탓할 수 없는 정당한 사유가 있다고 할 수는 없다."
    }
  ],
  "keyword_tagg": [
    {
      "id": 1,
      "keyword": "행정법규 위반"
    },
    {
      "id": 2,
      "keyword": "건설기술관리법"
    }
  ],
  "Reference_info": {
    "reference_rules": "건설기술관리법 제21조의4제1항, 제39조제1항 건설기술관리법 시행령 제127조제2항제4호 건설기술관리법 시행규칙 제27조, 제28조제1항, 별표10의 5.벌점의 측정기준 중 가. 번호 1.20",
    "reference_court_case": ""
  },
  "Class_info": {
    "class_name": "행정",
    "instance_name": "행정처분취소"
  }
}