{
  "info": {
    "id": 38020163,
    "dataType": "판결문",
    "caseNm": "일반음식점영업정지처분 취소청구",
    "caseTitle": "국민권익위원회 행심 제2010-026호, 2010. 2. 23.",
    "courtType": "심결례",
    "courtNm": "국민권익위원회",
    "judmnAdjuDe": "2010-02-23",
    "caseNoID": "행심 제2010-026호",
    "caseNo": "행심 제2010-026호"
  },
  "jdgmn": "",
  "jdgmnInfo": [
    {
      "question": "행정심판청구 및 소송결과 기각 결정된 사례가 있고, 현재까지 시정하지 않고 계속 영업을 하는 등의 위반행위에 대한 영업정지 처분은 정당한가?",
      "answer": "긍정"
    }
  ],
  "Summary": [
    {
      "summ_contxt": "청구인은 영업장면적을 임의로 확장한 사실이 없으며, 확장한 사실이 있다 하더라도 이는 종전영업자가 행한 일이므로 이를 인정할 수 없다고 주장하고 있으나, 청구인은 이 사건과 동일한 내용으로 2007. 12. 27. 행정심판을 청구하여 2008. 2. 27. 청구가 기각되었고, 행정소송을 제기하여 2009. 10. 16. 상고기각 된 사례를 확인할 수 있는바, 이는 청구인이 영업장 면적을 임의로 확장하여 영업을 한 사실은 인정된다 할 것이다.\n식품위생법령에서 영업자준수사항으로 영업장의 면적을 변경하고 변경신고를 하지 아니한 때에는 행정제재처분을 하도록 규정하고 있으며, 또한 청구인은 이 사건과 동일한 내용으로 행정심판청구 및 소송결과 기각 결정된 사례가 있고, 현재까지 시정하지 않고 계속 영업을 한 것으로 영업자의 지위로서 영업자준수사항을 위반한 책임을 면할 수 없다 할 것이므로 피청구인이 청구인에게 한 이 사건 처분에 위법·부당함은 없다 할 것이다.",
      "summ_pass": "식품위생법령에서 영업자준수사항으로 영업장의 면적을 변경하고 변경신고를 하지 아니한 때에는 행정제재처분을 하도록 규정하고 있으며, 또한 청구인은 이 사건과 동일한 내용으로 행정심판청구 및 소송결과 기각 결정된 사례가 있고, 현재까지 시정하지 않고 계속 영업을 한 것으로 영업자의 지위로서 영업자준수사항을 위반한 책임을 면할 수 없다 할 것이므로 피청구인이 청구인에게 한 이 사건 처분에 위법·부당함은 없다 할 것이다."
    }
  ],
  "keyword_tagg": [
    {
      "id": 1,
      "keyword": "영업장 면적"
    }
  ],
  "Reference_info": {
    "reference_rules": "○「식품위생법」 제36조, 제37조 및 제75조 ○「식품위생법 시행령」 제26조 ○「식품위생법 시행규칙」 제89조 [별표 23]",
    "reference_court_case": ""
  },
  "Class_info": {
    "class_name": "행정",
    "instance_name": "영업정지/영업허가"
  }
}